{"ABİDİN BEY": [{"t": "19.07.2026", "m1400": "", "m1200": "", "m1000": "1.03.90", "m800": "", "durum": "R", "tur": "Galop"}, {"t": "16.07.2026", "m1400": "", "m1200": "", "m1000": "", "m800": "", "durum": "R", "tur": "Galop"}, {"t": "12.07.2026", "m1400": "", "m1200": "", "m1000": "", "m800": "0.50.30", "durum": "R", "tur": "Galop"}, {"t": "27.06.2026", "m1400": "", "m1200": "", "m1000": "1.04.50", "m800": "", "durum": "R", "tur": "Galop"}, {"t": "25.06.2026", "m1400": "", "m1200": "", "m1000": "", "m800": "", "durum": "R", "tur": "Galop"}, {"t": "13.06.2026", "m1400": "", "m1200": "1.17.70", "m1000": "1.04.00", "m800": "", "durum": "R", "tur": "Galop"}], "AKBURÇAK": [{"t": "19.07.2026", "m1400": "", "m1200": "", "m1000": "", "m800": "0.57.50", "durum": "R", "tur": "Galop"}, {"t": "17.07.2026", "m1400": "", "m1200": "", "m1000": "", "m800": "", "durum": "R", "tur": "Galop"}, {"t": "30.06.2026", "m1400": "", "m1200": "", "m1000": "", "m800": "0.57.00", "durum": "Ç", "tur": "Galop"}, {"t": "24.06.2026", "m1400": "", "m1200": "", "m1000": "", "m800": "", "durum": "R", "tur": "Galop"}, {"t": "14.06.2026", "m1400": "", "m1200": "", "m1000": "", "m800": "1.00.00", "durum": "R", "tur": "Galop"}, {"t": "12.06.2026", "m1400": "", "m1200": "", "m1000": "", "m800": "", "durum": "R", "tur": "Galop"}], "AKIN BEYLİ": [{"t": "19.07.2026", "m1400": "", "m1200": "", "m1000": "", "m800": "0.51.50", "durum": "R", "tur": "Galop"}, {"t": "17.07.2026", "m1400": "", "m1200": "", "m1000": "", "m800": "", "durum": "R", "tur": "Galop"}, {"t": "01.07.2026", "m1400": "", "m1200": "", "m1000": "", "m800": "", "durum": "R", "tur": "Galop"}, {"t": "31.05.2026", "m1400": "", "m1200": "", "m1000": "", "m800": "", "durum": "R", "tur": "Galop"}, {"t": "24.04.2026", "m1400": "", "m1200": "", "m1000": "", "m800": "0.53.00", "durum": "R", "tur": "Galop"}, {"t": "02.04.2026", "m1400": "", "m1200": "", "m1000": "", "m800": "0.53.00", "durum": "R", "tur": "Galop"}], "AL YELE": [{"t": "17.07.2026", "m1400": "", "m1200": "", "m1000": "", "m800": "0.50.00", "durum": "R", "tur": "Galop"}, {"t": "15.07.2026", "m1400": "", "m1200": "", "m1000": "", "m800": "", "durum": "R", "tur": "Sprint"}, {"t": "29.06.2026", "m1400": "", "m1200": "", "m1000": "1.04.50", "m800": "", "durum": "R", "tur": "Galop"}, {"t": "25.06.2026", "m1400": "", "m1200": "", "m1000": "", "m800": "", "durum": "R", "tur": "Sprint"}, {"t": "22.06.2026", "m1400": "", "m1200": "", "m1000": "1.05.50", "m800": "", "durum": "R", "tur": "Galop"}, {"t": "15.06.2026", "m1400": "", "m1200": "", "m1000": "1.03.00", "m800": "", "durum": "R", "tur": "Galop"}], "ALÜNLÜHAT": [{"t": "05.07.2026", "m1400": "", "m1200": "", "m1000": "", "m800": "0.55.70", "durum": "R", "tur": "Galop"}, {"t": "03.07.2026", "m1400": "", "m1200": "", "m1000": "", "m800": "", "durum": "R", "tur": "Galop"}, {"t": "25.06.2026", "m1400": "", "m1200": "", "m1000": "", "m800": "", "durum": "R", "tur": "Galop"}, {"t": "21.06.2026", "m1400": "", "m1200": "", "m1000": "1.13.00", "m800": "", "durum": "R", "tur": "Galop"}, {"t": "12.06.2026", "m1400": "", "m1200": "", "m1000": "", "m800": "", "durum": "R", "tur": "Sprint"}, {"t": "24.05.2026", "m1400": "", "m1200": "", "m1000": "", "m800": "0.56.50", "durum": "R", "tur": "Galop"}], "ANADOLU YAZI": [{"t": "21.07.2026", "m1400": "", "m1200": "", "m1000": "", "m800": "", "durum": "R", "tur": "Galop"}, {"t": "12.07.2026", "m1400": "", "m1200": "", "m1000": "", "m800": "0.56.00", "durum": "R", "tur": "Galop"}, {"t": "10.07.2026", "m1400": "", "m1200": "", "m1000": "", "m800": "", "durum": "R", "tur": "Galop"}, {"t": "05.07.2026", "m1400": "", "m1200": "", "m1000": "", "m800": "0.59.50", "durum": "R", "tur": "Galop"}, {"t": "03.07.2026", "m1400": "", "m1200": "", "m1000": "", "m800": "", "durum": "R", "tur": "Galop"}, {"t": "14.06.2026", "m1400": "", "m1200": "", "m1000": "", "m800": "0.56.30", "durum": "R", "tur": "Galop"}], "ANKARA GÜZELİ": [{"t": "19.07.2026", "m1400": "", "m1200": "", "m1000": "", "m800": "0.57.00", "durum": "R", "tur": "Galop"}, {"t": "05.07.2026", "m1400": "", "m1200": "", "m1000": "", "m800": "0.57.50", "durum": "R", "tur": "Galop"}, {"t": "24.06.2026", "m1400": "", "m1200": "", "m1000": "", "m800": "0.57.00", "durum": "R", "tur": "Galop"}, {"t": "07.06.2026", "m1400": "", "m1200": "", "m1000": "", "m800": "0.57.00", "durum": "R", "tur": "Galop"}, {"t": "24.05.2026", "m1400": "", "m1200": "", "m1000": "", "m800": "0.57.00", "durum": "R", "tur": "Galop"}, {"t": "10.05.2026", "m1400": "", "m1200": "", "m1000": "", "m800": "", "durum": "R", "tur": "Galop"}], "ANSHBA SKY": [{"t": "17.07.2026", "m1400": "", "m1200": "", "m1000": "", "m800": "0.50.00", "durum": "R", "tur": "Galop"}, {"t": "15.07.2026", "m1400": "", "m1200": "", "m1000": "", "m800": "", "durum": "R", "tur": "Sprint"}, {"t": "29.06.2026", "m1400": "", "m1200": "", "m1000": "1.04.00", "m800": "", "durum": "R", "tur": "Galop"}, {"t": "22.06.2026", "m1400": "", "m1200": "", "m1000": "1.04.20", "m800": "", "durum": "R", "tur": "Galop"}, {"t": "08.06.2026", "m1400": "", "m1200": "", "m1000": "", "m800": "0.50.00", "durum": "R", "tur": "Galop"}, {"t": "01.06.2026", "m1400": "", "m1200": "", "m1000": "1.03.40", "m800": "", "durum": "R", "tur": "Galop"}], "ASTARA LAÇİN": [{"t": "19.07.2026", "m1400": "", "m1200": "", "m1000": "", "m800": "0.56.70", "durum": "R", "tur": "Galop"}, {"t": "16.07.2026", "m1400": "", "m1200": "", "m1000": "", "m800": "", "durum": "R", "tur": "Galop"}, {"t": "09.07.2026", "m1400": "", "m1200": "", "m1000": "", "m800": "", "durum": "R", "tur": "Galop"}, {"t": "28.06.2026", "m1400": "", "m1200": "", "m1000": "", "m800": "0.55.80", "durum": "R", "tur": "Galop"}, {"t": "30.05.2026", "m1400": "", "m1200": "", "m1000": "", "m800": "", "durum": "R", "tur": "Sprint"}, {"t": "22.05.2026", "m1400": "", "m1200": "", "m1000": "", "m800": "", "durum": "R", "tur": "Galop"}], "ATLI FIRTINA": [{"t": "21.07.2026", "m1400": "", "m1200": "", "m1000": "", "m800": "0.57.50", "durum": "R", "tur": "Galop"}, {"t": "07.07.2026", "m1400": "", "m1200": "", "m1000": "", "m800": "0.57.80", "durum": "R", "tur": "Galop"}, {"t": "25.06.2026", "m1400": "", "m1200": "", "m1000": "", "m800": "", "durum": "R", "tur": "Galop"}, {"t": "18.06.2026", "m1400": "", "m1200": "", "m1000": "", "m800": "0.54.90", "durum": "R", "tur": "Galop"}, {"t": "07.06.2026", "m1400": "", "m1200": "", "m1000": "", "m800": "0.57.00", "durum": "R", "tur": "Galop"}, {"t": "31.05.2026", "m1400": "", "m1200": "", "m1000": "", "m800": "0.56.10", "durum": "R", "tur": "Galop"}], "BAHARBAHİR": [{"t": "21.07.2026", "m1400": "", "m1200": "", "m1000": "", "m800": "", "durum": "R", "tur": "Galop"}, {"t": "07.07.2026", "m1400": "", "m1200": "", "m1000": "", "m800": "0.59.00", "durum": "R", "tur": "Galop"}, {"t": "05.07.2026", "m1400": "", "m1200": "", "m1000": "", "m800": "0.57.50", "durum": "R", "tur": "Galop"}, {"t": "28.06.2026", "m1400": "", "m1200": "", "m1000": "", "m800": "0.56.40", "durum": "R", "tur": "Galop"}, {"t": "24.06.2026", "m1400": "", "m1200": "", "m1000": "", "m800": "", "durum": "R", "tur": "Sprint"}, {"t": "14.06.2026", "m1400": "", "m1200": "", "m1000": "", "m800": "0.58.00", "durum": "R", "tur": "Galop"}], "BELLİ BEY": [{"t": "14.07.2026", "m1400": "", "m1200": "", "m1000": "", "m800": "", "durum": "R", "tur": "Galop"}, {"t": "04.07.2026", "m1400": "", "m1200": "", "m1000": "", "m800": "0.59.30", "durum": "R", "tur": "Galop"}, {"t": "13.06.2026", "m1400": "", "m1200": "", "m1000": "", "m800": "0.56.70", "durum": "R", "tur": "Galop"}, {"t": "11.06.2026", "m1400": "", "m1200": "", "m1000": "", "m800": "", "durum": "R", "tur": "Sprint"}, {"t": "30.05.2026", "m1400": "", "m1200": "", "m1000": "", "m800": "1.00.00", "durum": "Ç", "tur": "Galop"}, {"t": "16.05.2026", "m1400": "", "m1200": "", "m1000": "", "m800": "", "durum": "Ç", "tur": "Galop"}], "BLACK PIPELINE": [{"t": "19.07.2026", "m1400": "", "m1200": "", "m1000": "", "m800": "0.51.30", "durum": "R", "tur": "Galop"}, {"t": "02.07.2026", "m1400": "", "m1200": "", "m1000": "", "m800": "", "durum": "R", "tur": "Galop"}, {"t": "28.06.2026", "m1400": "", "m1200": "", "m1000": "1.05.40", "m800": "", "durum": "R", "tur": "Galop"}, {"t": "21.06.2026", "m1400": "", "m1200": "", "m1000": "", "m800": "0.51.00", "durum": "R", "tur": "Galop"}, {"t": "07.06.2026", "m1400": "", "m1200": "", "m1000": "", "m800": "0.52.00", "durum": "R", "tur": "Galop"}, {"t": "31.05.2026", "m1400": "", "m1200": "", "m1000": "", "m800": "0.51.80", "durum": "R", "tur": "Galop"}], "BİZİMSOY": [{"t": "21.07.2026", "m1400": "", "m1200": "", "m1000": "", "m800": "0.57.70", "durum": "R", "tur": "Galop"}, {"t": "12.07.2026", "m1400": "", "m1200": "", "m1000": "", "m800": "0.57.00", "durum": "R", "tur": "Galop"}, {"t": "06.06.2026", "m1400": "", "m1200": "", "m1000": "", "m800": "", "durum": "R", "tur": "Galop"}, {"t": "28.05.2026", "m1400": "", "m1200": "", "m1000": "", "m800": "", "durum": "HÇ", "tur": "Galop"}, {"t": "23.05.2026", "m1400": "", "m1200": "", "m1000": "", "m800": "", "durum": "HÇ", "tur": "Galop"}, {"t": "02.05.2026", "m1400": "", "m1200": "", "m1000": "", "m800": "", "durum": "R", "tur": "Sprint"}], "CATALYST": [{"t": "19.07.2026", "m1400": "", "m1200": "", "m1000": "", "m800": "", "durum": "R", "tur": "Galop"}, {"t": "17.07.2026", "m1400": "", "m1200": "", "m1000": "", "m800": "", "durum": "R", "tur": "Sprint"}, {"t": "12.07.2026", "m1400": "", "m1200": "", "m1000": "1.03.50", "m800": "", "durum": "R", "tur": "Galop"}, {"t": "10.07.2026", "m1400": "", "m1200": "", "m1000": "", "m800": "", "durum": "R", "tur": "Galop"}, {"t": "05.07.2026", "m1400": "", "m1200": "", "m1000": "1.04.00", "m800": "", "durum": "R", "tur": "Galop"}, {"t": "03.07.2026", "m1400": "", "m1200": "", "m1000": "", "m800": "", "durum": "R", "tur": "Galop"}], "CEYHAN SULTANI": [{"t": "21.07.2026", "m1400": "", "m1200": "", "m1000": "", "m800": "", "durum": "R", "tur": "Galop"}, {"t": "11.07.2026", "m1400": "", "m1200": "", "m1000": "", "m800": "", "durum": "R", "tur": "Sprint"}, {"t": "02.07.2026", "m1400": "", "m1200": "", "m1000": "", "m800": "", "durum": "R", "tur": "Galop"}, {"t": "28.06.2026", "m1400": "", "m1200": "", "m1000": "", "m800": "0.51.00", "durum": "R", "tur": "Galop"}, {"t": "26.06.2026", "m1400": "", "m1200": "", "m1000": "", "m800": "", "durum": "R", "tur": "Galop"}, {"t": "21.06.2026", "m1400": "", "m1200": "", "m1000": "", "m800": "0.51.30", "durum": "R", "tur": "Galop"}], "DENİZ KASIRGASI": [{"t": "21.07.2026", "m1400": "", "m1200": "", "m1000": "", "m800": "0.57.50", "durum": "R", "tur": "Galop"}, {"t": "12.07.2026", "m1400": "", "m1200": "", "m1000": "", "m800": "0.56.00", "durum": "R", "tur": "Galop"}, {"t": "06.06.2026", "m1400": "", "m1200": "", "m1000": "", "m800": "", "durum": "R", "tur": "Galop"}, {"t": "28.05.2026", "m1400": "", "m1200": "", "m1000": "", "m800": "", "durum": "HÇ", "tur": "Galop"}, {"t": "23.05.2026", "m1400": "", "m1200": "", "m1000": "", "m800": "", "durum": "R", "tur": "Galop"}, {"t": "09.05.2026", "m1400": "", "m1200": "", "m1000": "", "m800": "", "durum": "R", "tur": "Galop"}], "DENİZ SAVAŞI": [{"t": "19.07.2026", "m1400": "", "m1200": "", "m1000": "1.12.50", "m800": "", "durum": "R", "tur": "Galop"}, {"t": "17.07.2026", "m1400": "", "m1200": "", "m1000": "", "m800": "", "durum": "R", "tur": "Galop"}, {"t": "07.07.2026", "m1400": "", "m1200": "", "m1000": "", "m800": "", "durum": "R", "tur": "Galop"}, {"t": "25.06.2026", "m1400": "", "m1200": "", "m1000": "", "m800": "", "durum": "R", "tur": "Sprint"}, {"t": "18.06.2026", "m1400": "", "m1200": "", "m1000": "", "m800": "", "durum": "R", "tur": "Sprint"}, {"t": "09.06.2026", "m1400": "", "m1200": "", "m1000": "", "m800": "0.57.50", "durum": "R", "tur": "Galop"}], "EL VERDUGO": [{"t": "21.07.2026", "m1400": "", "m1200": "", "m1000": "", "m800": "", "durum": "R", "tur": "Kenter"}, {"t": "13.07.2026", "m1400": "", "m1200": "", "m1000": "", "m800": "0.52.60", "durum": "Ç", "tur": "Galop"}, {"t": "15.06.2026", "m1400": "", "m1200": "", "m1000": "", "m800": "0.53.00", "durum": "R", "tur": "Galop"}, {"t": "27.05.2026", "m1400": "", "m1200": "", "m1000": "", "m800": "", "durum": "R", "tur": "Sprint"}, {"t": "17.05.2026", "m1400": "", "m1200": "", "m1000": "", "m800": "0.51.00", "durum": "R", "tur": "Galop"}, {"t": "01.05.2026", "m1400": "", "m1200": "", "m1000": "", "m800": "0.50.20", "durum": "R", "tur": "Galop"}], "ERSELEFE": [{"t": "19.07.2026", "m1400": "", "m1200": "", "m1000": "", "m800": "0.58.20", "durum": "R", "tur": "Galop"}, {"t": "12.07.2026", "m1400": "", "m1200": "", "m1000": "", "m800": "", "durum": "R", "tur": "Sprint"}, {"t": "05.07.2026", "m1400": "", "m1200": "", "m1000": "1.09.50", "m800": "", "durum": "R", "tur": "Galop"}, {"t": "03.07.2026", "m1400": "", "m1200": "", "m1000": "", "m800": "", "durum": "R", "tur": "Sprint"}, {"t": "19.06.2026", "m1400": "", "m1200": "", "m1000": "", "m800": "0.56.30", "durum": "R", "tur": "Galop"}, {"t": "14.06.2026", "m1400": "", "m1200": "", "m1000": "1.12.20", "m800": "", "durum": "R", "tur": "Galop"}], "EYLÜLSEL": [{"t": "21.07.2026", "m1400": "", "m1200": "", "m1000": "", "m800": "", "durum": "R", "tur": "Sprint"}, {"t": "12.07.2026", "m1400": "", "m1200": "", "m1000": "", "m800": "0.56.50", "durum": "R", "tur": "Galop"}, {"t": "10.07.2026", "m1400": "", "m1200": "", "m1000": "", "m800": "", "durum": "R", "tur": "Galop"}, {"t": "05.07.2026", "m1400": "", "m1200": "", "m1000": "", "m800": "0.57.50", "durum": "R", "tur": "Galop"}, {"t": "03.07.2026", "m1400": "", "m1200": "", "m1000": "", "m800": "", "durum": "R", "tur": "Galop"}, {"t": "24.06.2026", "m1400": "", "m1200": "", "m1000": "", "m800": "", "durum": "R", "tur": "Galop"}], "EİKO": [{"t": "19.07.2026", "m1400": "", "m1200": "", "m1000": "", "m800": "0.51.00", "durum": "R", "tur": "Galop"}, {"t": "06.07.2026", "m1400": "", "m1200": "", "m1000": "", "m800": "0.50.10", "durum": "R", "tur": "Galop"}, {"t": "24.06.2026", "m1400": "", "m1200": "", "m1000": "", "m800": "0.49.80", "durum": "R", "tur": "Galop"}, {"t": "11.06.2026", "m1400": "", "m1200": "", "m1000": "", "m800": "", "durum": "R", "tur": "Galop"}, {"t": "06.06.2026", "m1400": "", "m1200": "", "m1000": "", "m800": "0.50.50", "durum": "R", "tur": "Galop"}, {"t": "25.05.2026", "m1400": "", "m1200": "", "m1000": "", "m800": "0.51.20", "durum": "R", "tur": "Galop"}], "FEMALE WARRIOR": [{"t": "20.07.2026", "m1400": "", "m1200": "", "m1000": "", "m800": "0.50.00", "durum": "R", "tur": "Galop"}, {"t": "28.06.2026", "m1400": "", "m1200": "", "m1000": "", "m800": "0.49.00", "durum": "R", "tur": "Galop"}, {"t": "25.06.2026", "m1400": "", "m1200": "", "m1000": "", "m800": "", "durum": "R", "tur": "Sprint"}, {"t": "16.06.2026", "m1400": "", "m1200": "", "m1000": "", "m800": "", "durum": "R", "tur": "Sprint"}, {"t": "31.05.2026", "m1400": "", "m1200": "", "m1000": "", "m800": "0.49.00", "durum": "R", "tur": "Galop"}, {"t": "24.05.2026", "m1400": "", "m1200": "", "m1000": "", "m800": "0.51.50", "durum": "R", "tur": "Galop"}], "GAZNELİ": [{"t": "19.07.2026", "m1400": "", "m1200": "", "m1000": "", "m800": "0.57.00", "durum": "R", "tur": "Galop"}, {"t": "05.07.2026", "m1400": "", "m1200": "", "m1000": "", "m800": "0.57.50", "durum": "R", "tur": "Galop"}, {"t": "24.06.2026", "m1400": "", "m1200": "", "m1000": "", "m800": "", "durum": "R", "tur": "Galop"}, {"t": "18.06.2026", "m1400": "", "m1200": "", "m1000": "", "m800": "0.54.20", "durum": "R", "tur": "Galop"}, {"t": "07.06.2026", "m1400": "", "m1200": "", "m1000": "", "m800": "0.57.00", "durum": "R", "tur": "Galop"}, {"t": "28.05.2026", "m1400": "", "m1200": "", "m1000": "", "m800": "", "durum": "R", "tur": "Galop"}], "GOLDEN BEE": [{"t": "19.07.2026", "m1400": "", "m1200": "", "m1000": "1.04.00", "m800": "", "durum": "R", "tur": "Galop"}, {"t": "16.07.2026", "m1400": "", "m1200": "", "m1000": "", "m800": "0.53.90", "durum": "R", "tur": "Galop"}, {"t": "12.07.2026", "m1400": "", "m1200": "", "m1000": "1.04.50", "m800": "", "durum": "R", "tur": "Galop"}, {"t": "09.07.2026", "m1400": "", "m1200": "", "m1000": "", "m800": "", "durum": "R", "tur": "Galop"}, {"t": "28.06.2026", "m1400": "", "m1200": "", "m1000": "1.04.30", "m800": "", "durum": "R", "tur": "Galop"}, {"t": "25.06.2026", "m1400": "", "m1200": "", "m1000": "", "m800": "", "durum": "R", "tur": "Galop"}], "GOLDEN PROMISE": [{"t": "19.07.2026", "m1400": "", "m1200": "", "m1000": "1.04.00", "m800": "", "durum": "R", "tur": "Galop"}, {"t": "16.07.2026", "m1400": "", "m1200": "", "m1000": "", "m800": "", "durum": "R", "tur": "Galop"}, {"t": "26.06.2026", "m1400": "", "m1200": "", "m1000": "", "m800": "", "durum": "R", "tur": "Galop"}, {"t": "13.06.2026", "m1400": "", "m1200": "", "m1000": "1.04.00", "m800": "", "durum": "R", "tur": "Galop"}, {"t": "28.05.2026", "m1400": "", "m1200": "", "m1000": "", "m800": "", "durum": "R", "tur": "Galop"}, {"t": "24.05.2026", "m1400": "", "m1200": "", "m1000": "", "m800": "0.51.20", "durum": "R", "tur": "Galop"}], "GÜLLÜ BAHÇE": [{"t": "12.07.2026", "m1400": "", "m1200": "", "m1000": "", "m800": "", "durum": "R", "tur": "Galop"}, {"t": "28.06.2026", "m1400": "", "m1200": "", "m1000": "", "m800": "0.58.20", "durum": "HR", "tur": "Galop"}, {"t": "10.04.2026", "m1400": "", "m1200": "", "m1000": "", "m800": "", "durum": "R", "tur": "Sprint"}, {"t": "05.04.2026", "m1400": "", "m1200": "", "m1000": "", "m800": "", "durum": "R", "tur": "Galop"}, {"t": "29.03.2026", "m1400": "", "m1200": "", "m1000": "", "m800": "", "durum": "R", "tur": "Galop"}, {"t": "15.03.2026", "m1400": "", "m1200": "", "m1000": "", "m800": "0.59.00", "durum": "R", "tur": "Galop"}], "GÜNEYİM": [{"t": "19.07.2026", "m1400": "", "m1200": "", "m1000": "", "m800": "0.53.50", "durum": "R", "tur": "Galop"}, {"t": "02.07.2026", "m1400": "", "m1200": "", "m1000": "", "m800": "", "durum": "R", "tur": "Galop"}, {"t": "28.06.2026", "m1400": "", "m1200": "", "m1000": "", "m800": "0.51.00", "durum": "R", "tur": "Galop"}, {"t": "21.06.2026", "m1400": "", "m1200": "", "m1000": "", "m800": "", "durum": "R", "tur": "Galop"}, {"t": "07.06.2026", "m1400": "", "m1200": "", "m1000": "", "m800": "0.53.50", "durum": "R", "tur": "Galop"}, {"t": "05.06.2026", "m1400": "", "m1200": "", "m1000": "", "m800": "", "durum": "R", "tur": "Galop"}], "GÜNGELDİ AĞA": [{"t": "12.07.2026", "m1400": "", "m1200": "", "m1000": "", "m800": "0.57.20", "durum": "R", "tur": "Galop"}, {"t": "10.07.2026", "m1400": "", "m1200": "", "m1000": "", "m800": "", "durum": "R", "tur": "Galop"}, {"t": "03.07.2026", "m1400": "", "m1200": "", "m1000": "", "m800": "", "durum": "R", "tur": "Sprint"}, {"t": "18.06.2026", "m1400": "", "m1200": "", "m1000": "", "m800": "0.56.20", "durum": "R", "tur": "Galop"}, {"t": "11.06.2026", "m1400": "", "m1200": "", "m1000": "", "m800": "", "durum": "R", "tur": "Galop"}, {"t": "07.06.2026", "m1400": "", "m1200": "", "m1000": "", "m800": "1.01.90", "durum": "R", "tur": "Galop"}], "HAZAN SABAHI": [{"t": "19.07.2026", "m1400": "", "m1200": "", "m1000": "", "m800": "0.57.00", "durum": "R", "tur": "Galop"}, {"t": "05.07.2026", "m1400": "", "m1200": "", "m1000": "", "m800": "0.57.40", "durum": "R", "tur": "Galop"}, {"t": "03.07.2026", "m1400": "", "m1200": "", "m1000": "", "m800": "", "durum": "R", "tur": "Sprint"}, {"t": "24.06.2026", "m1400": "", "m1200": "", "m1000": "", "m800": "", "durum": "R", "tur": "Sprint"}, {"t": "21.06.2026", "m1400": "", "m1200": "", "m1000": "", "m800": "0.57.00", "durum": "R", "tur": "Galop"}, {"t": "14.06.2026", "m1400": "", "m1200": "", "m1000": "", "m800": "0.55.70", "durum": "R", "tur": "Galop"}], "HIDDEN ISLAND": [{"t": "21.07.2026", "m1400": "", "m1200": "", "m1000": "1.03.30", "m800": "", "durum": "R", "tur": "Galop"}, {"t": "17.07.2026", "m1400": "", "m1200": "", "m1000": "", "m800": "", "durum": "R", "tur": "Galop"}, {"t": "12.07.2026", "m1400": "", "m1200": "", "m1000": "", "m800": "0.51.90", "durum": "R", "tur": "Galop"}, {"t": "02.07.2026", "m1400": "", "m1200": "", "m1000": "", "m800": "0.50.00", "durum": "R", "tur": "Galop"}, {"t": "28.06.2026", "m1400": "", "m1200": "", "m1000": "1.05.30", "m800": "", "durum": "R", "tur": "Galop"}, {"t": "26.06.2026", "m1400": "", "m1200": "", "m1000": "", "m800": "", "durum": "R", "tur": "Galop"}], "KARAMAÇABEY": [{"t": "19.07.2026", "m1400": "", "m1200": "", "m1000": "", "m800": "0.53.00", "durum": "R", "tur": "Galop"}, {"t": "17.07.2026", "m1400": "", "m1200": "", "m1000": "", "m800": "", "durum": "R", "tur": "Sprint"}, {"t": "02.07.2026", "m1400": "", "m1200": "", "m1000": "", "m800": "0.51.00", "durum": "R", "tur": "Galop"}, {"t": "21.06.2026", "m1400": "", "m1200": "", "m1000": "1.04.50", "m800": "", "durum": "R", "tur": "Galop"}, {"t": "19.06.2026", "m1400": "", "m1200": "", "m1000": "", "m800": "", "durum": "R", "tur": "Galop"}, {"t": "07.06.2026", "m1400": "", "m1200": "", "m1000": "", "m800": "0.50.60", "durum": "R", "tur": "Galop"}], "KARDAHA": [{"t": "19.07.2026", "m1400": "", "m1200": "", "m1000": "", "m800": "0.51.00", "durum": "R", "tur": "Galop"}, {"t": "17.07.2026", "m1400": "", "m1200": "", "m1000": "", "m800": "", "durum": "R", "tur": "Galop"}, {"t": "30.06.2026", "m1400": "", "m1200": "", "m1000": "", "m800": "", "durum": "R", "tur": "Galop"}, {"t": "28.06.2026", "m1400": "", "m1200": "", "m1000": "", "m800": "0.51.60", "durum": "R", "tur": "Galop"}, {"t": "23.06.2026", "m1400": "", "m1200": "", "m1000": "", "m800": "0.52.50", "durum": "R", "tur": "Galop"}, {"t": "19.06.2026", "m1400": "", "m1200": "", "m1000": "", "m800": "", "durum": "R", "tur": "Galop"}], "KEMİK KAPTAN": [{"t": "21.07.2026", "m1400": "", "m1200": "", "m1000": "", "m800": "", "durum": "R", "tur": "Galop"}, {"t": "16.07.2026", "m1400": "", "m1200": "", "m1000": "1.10.50", "m800": "", "durum": "R", "tur": "Galop"}, {"t": "14.07.2026", "m1400": "", "m1200": "", "m1000": "", "m800": "", "durum": "R", "tur": "Galop"}, {"t": "09.07.2026", "m1400": "", "m1200": "1.27.00", "m1000": "1.12.30", "m800": "", "durum": "R", "tur": "Galop"}, {"t": "07.07.2026", "m1400": "", "m1200": "", "m1000": "", "m800": "", "durum": "R", "tur": "Galop"}, {"t": "28.06.2026", "m1400": "", "m1200": "", "m1000": "1.11.20", "m800": "", "durum": "R", "tur": "Galop"}], "KIZIM BİNDAL": [{"t": "18.07.2026", "m1400": "", "m1200": "", "m1000": "", "m800": "1.00.50", "durum": "ÇR", "tur": "Galop"}, {"t": "04.07.2026", "m1400": "", "m1200": "", "m1000": "", "m800": "0.57.30", "durum": "R", "tur": "Galop"}, {"t": "02.07.2026", "m1400": "", "m1200": "", "m1000": "", "m800": "", "durum": "R", "tur": "Sprint"}, {"t": "27.06.2026", "m1400": "", "m1200": "", "m1000": "", "m800": "1.02.30", "durum": "Ç", "tur": "Galop"}, {"t": "18.04.2026", "m1400": "", "m1200": "", "m1000": "", "m800": "0.56.00", "durum": "Ç", "tur": "Galop"}, {"t": "11.04.2026", "m1400": "", "m1200": "", "m1000": "", "m800": "0.57.10", "durum": "HÇ", "tur": "Galop"}], "LEADER TULIP": [{"t": "19.07.2026", "m1400": "", "m1200": "", "m1000": "", "m800": "0.50.80", "durum": "R", "tur": "Galop"}, {"t": "17.07.2026", "m1400": "", "m1200": "", "m1000": "", "m800": "", "durum": "R", "tur": "Sprint"}, {"t": "12.07.2026", "m1400": "", "m1200": "", "m1000": "", "m800": "0.51.00", "durum": "R", "tur": "Galop"}, {"t": "28.06.2026", "m1400": "", "m1200": "", "m1000": "", "m800": "0.50.80", "durum": "R", "tur": "Galop"}, {"t": "21.06.2026", "m1400": "", "m1200": "", "m1000": "", "m800": "0.51.00", "durum": "R", "tur": "Galop"}, {"t": "14.06.2026", "m1400": "", "m1200": "", "m1000": "", "m800": "0.50.30", "durum": "R", "tur": "Galop"}], "LOVE OF AMERICA": [{"t": "17.07.2026", "m1400": "", "m1200": "", "m1000": "1.04.00", "m800": "", "durum": "R", "tur": "Galop"}, {"t": "10.07.2026", "m1400": "", "m1200": "", "m1000": "", "m800": "", "durum": "R", "tur": "Galop"}, {"t": "26.06.2026", "m1400": "", "m1200": "", "m1000": "", "m800": "0.52.60", "durum": "R", "tur": "Galop"}, {"t": "14.06.2026", "m1400": "", "m1200": "", "m1000": "", "m800": "0.51.50", "durum": "R", "tur": "Galop"}, {"t": "12.06.2026", "m1400": "", "m1200": "", "m1000": "", "m800": "", "durum": "R", "tur": "Galop"}, {"t": "07.06.2026", "m1400": "", "m1200": "", "m1000": "", "m800": "0.51.50", "durum": "R", "tur": "Galop"}], "MEYDAN OKU": [{"t": "19.07.2026", "m1400": "", "m1200": "", "m1000": "", "m800": "0.51.40", "durum": "R", "tur": "Galop"}, {"t": "03.07.2026", "m1400": "", "m1200": "", "m1000": "", "m800": "", "durum": "R", "tur": "Sprint"}, {"t": "28.06.2026", "m1400": "", "m1200": "", "m1000": "", "m800": "0.51.80", "durum": "R", "tur": "Galop"}, {"t": "16.06.2026", "m1400": "", "m1200": "", "m1000": "", "m800": "", "durum": "R", "tur": "Galop"}, {"t": "07.06.2026", "m1400": "", "m1200": "", "m1000": "", "m800": "0.51.00", "durum": "R", "tur": "Galop"}, {"t": "05.06.2026", "m1400": "", "m1200": "", "m1000": "", "m800": "", "durum": "R", "tur": "Galop"}], "MUTLU BAHAR": [{"t": "21.07.2026", "m1400": "", "m1200": "", "m1000": "", "m800": "", "durum": "R", "tur": "Galop"}, {"t": "07.07.2026", "m1400": "", "m1200": "", "m1000": "", "m800": "0.56.60", "durum": "R", "tur": "Galop"}, {"t": "05.07.2026", "m1400": "", "m1200": "", "m1000": "", "m800": "", "durum": "R", "tur": "Sprint"}, {"t": "28.06.2026", "m1400": "", "m1200": "", "m1000": "", "m800": "0.55.00", "durum": "R", "tur": "Galop"}, {"t": "26.06.2026", "m1400": "", "m1200": "", "m1000": "", "m800": "", "durum": "R", "tur": "Sprint"}, {"t": "21.06.2026", "m1400": "", "m1200": "", "m1000": "", "m800": "", "durum": "R", "tur": "Galop"}], "MİR KARTALI": [{"t": "22.07.2026", "m1400": "", "m1200": "", "m1000": "", "m800": "", "durum": "R", "tur": "Sprint"}, {"t": "04.07.2026", "m1400": "", "m1200": "", "m1000": "", "m800": "", "durum": "HÇ", "tur": "Galop"}, {"t": "13.06.2026", "m1400": "", "m1200": "", "m1000": "", "m800": "0.55.80", "durum": "R", "tur": "Galop"}, {"t": "06.06.2026", "m1400": "", "m1200": "", "m1000": "", "m800": "0.57.80", "durum": "R", "tur": "Galop"}, {"t": "30.05.2026", "m1400": "", "m1200": "", "m1000": "", "m800": "0.58.20", "durum": "HR", "tur": "Galop"}, {"t": "16.05.2026", "m1400": "", "m1200": "", "m1000": "", "m800": "", "durum": "ÇR", "tur": "Galop"}], "O BİR VAHŞİ": [{"t": "12.07.2026", "m1400": "", "m1200": "", "m1000": "", "m800": "0.50.80", "durum": "R", "tur": "Galop"}, {"t": "10.07.2026", "m1400": "", "m1200": "", "m1000": "", "m800": "", "durum": "R", "tur": "Sprint"}, {"t": "05.07.2026", "m1400": "", "m1200": "", "m1000": "1.04.00", "m800": "", "durum": "R", "tur": "Galop"}, {"t": "28.06.2026", "m1400": "", "m1200": "", "m1000": "1.05.80", "m800": "", "durum": "R", "tur": "Galop"}, {"t": "21.06.2026", "m1400": "", "m1200": "", "m1000": "", "m800": "0.52.40", "durum": "R", "tur": "Galop"}, {"t": "14.06.2026", "m1400": "", "m1200": "", "m1000": "", "m800": "0.51.00", "durum": "R", "tur": "Galop"}], "PALURİ MAN": [{"t": "19.07.2026", "m1400": "", "m1200": "", "m1000": "1.07.80", "m800": "0.53.00", "durum": "R", "tur": "Galop"}, {"t": "16.07.2026", "m1400": "", "m1200": "", "m1000": "", "m800": "", "durum": "R", "tur": "Galop"}, {"t": "28.06.2026", "m1400": "", "m1200": "", "m1000": "", "m800": "", "durum": "ÇR", "tur": "Galop"}, {"t": "25.06.2026", "m1400": "", "m1200": "", "m1000": "", "m800": "", "durum": "ÇR", "tur": "Galop"}, {"t": "21.06.2026", "m1400": "", "m1200": "", "m1000": "1.09.00", "m800": "0.54.20", "durum": "R", "tur": "Galop"}, {"t": "03.06.2026", "m1400": "", "m1200": "", "m1000": "", "m800": "0.53.00", "durum": "ÇR", "tur": "Galop"}], "PRENSES BELBUS": [{"t": "19.07.2026", "m1400": "", "m1200": "", "m1000": "", "m800": "0.51.50", "durum": "R", "tur": "Galop"}, {"t": "16.07.2026", "m1400": "", "m1200": "", "m1000": "", "m800": "", "durum": "R", "tur": "Galop"}, {"t": "09.07.2026", "m1400": "", "m1200": "", "m1000": "", "m800": "", "durum": "R", "tur": "Galop"}, {"t": "26.06.2026", "m1400": "", "m1200": "", "m1000": "", "m800": "", "durum": "R", "tur": "Galop"}, {"t": "21.06.2026", "m1400": "", "m1200": "", "m1000": "", "m800": "0.52.00", "durum": "R", "tur": "Galop"}, {"t": "07.06.2026", "m1400": "", "m1200": "", "m1000": "", "m800": "0.50.60", "durum": "R", "tur": "Galop"}], "PRENSES MAVİŞ": [{"t": "21.07.2026", "m1400": "", "m1200": "", "m1000": "", "m800": "", "durum": "R", "tur": "Galop"}, {"t": "12.07.2026", "m1400": "", "m1200": "1.16.80", "m1000": "1.03.00", "m800": "", "durum": "R", "tur": "Galop"}, {"t": "10.07.2026", "m1400": "", "m1200": "", "m1000": "", "m800": "", "durum": "R", "tur": "Galop"}, {"t": "04.07.2026", "m1400": "", "m1200": "", "m1000": "1.03.60", "m800": "", "durum": "R", "tur": "Galop"}, {"t": "28.06.2026", "m1400": "", "m1200": "", "m1000": "1.04.90", "m800": "", "durum": "R", "tur": "Galop"}, {"t": "21.06.2026", "m1400": "", "m1200": "", "m1000": "", "m800": "0.54.00", "durum": "R", "tur": "Galop"}], "QUEEN BELLA": [{"t": "19.07.2026", "m1400": "", "m1200": "", "m1000": "1.14.30", "m800": "", "durum": "R", "tur": "Galop"}, {"t": "16.07.2026", "m1400": "", "m1200": "", "m1000": "", "m800": "", "durum": "R", "tur": "Galop"}, {"t": "10.07.2026", "m1400": "", "m1200": "", "m1000": "", "m800": "", "durum": "R", "tur": "Sprint"}, {"t": "04.07.2026", "m1400": "", "m1200": "", "m1000": "", "m800": "1.02.50", "durum": "ÇR", "tur": "Galop"}, {"t": "02.07.2026", "m1400": "", "m1200": "", "m1000": "", "m800": "", "durum": "R", "tur": "Galop"}, {"t": "28.06.2026", "m1400": "", "m1200": "", "m1000": "", "m800": "", "durum": "ÇR", "tur": "Galop"}], "QUEEN LARA": [{"t": "12.07.2026", "m1400": "", "m1200": "", "m1000": "", "m800": "", "durum": "R", "tur": "Galop"}, {"t": "10.07.2026", "m1400": "", "m1200": "", "m1000": "", "m800": "", "durum": "R", "tur": "Sprint"}, {"t": "07.06.2026", "m1400": "", "m1200": "", "m1000": "", "m800": "0.52.20", "durum": "R", "tur": "Galop"}, {"t": "05.06.2026", "m1400": "", "m1200": "", "m1000": "", "m800": "", "durum": "R", "tur": "Galop"}, {"t": "31.05.2026", "m1400": "", "m1200": "", "m1000": "", "m800": "", "durum": "R", "tur": "Galop"}, {"t": "24.05.2026", "m1400": "", "m1200": "", "m1000": "", "m800": "0.52.50", "durum": "R", "tur": "Galop"}], "RAHİME ABLA": [{"t": "19.07.2026", "m1400": "", "m1200": "", "m1000": "", "m800": "0.58.50", "durum": "R", "tur": "Galop"}, {"t": "17.07.2026", "m1400": "", "m1200": "", "m1000": "", "m800": "", "durum": "R", "tur": "Sprint"}, {"t": "11.06.2026", "m1400": "", "m1200": "", "m1000": "", "m800": "", "durum": "R", "tur": "Galop"}, {"t": "28.05.2026", "m1400": "", "m1200": "", "m1000": "", "m800": "", "durum": "R", "tur": "Galop"}, {"t": "16.04.2026", "m1400": "", "m1200": "", "m1000": "", "m800": "", "durum": "Ç", "tur": "Sprint"}, {"t": "11.04.2026", "m1400": "", "m1200": "", "m1000": "", "m800": "", "durum": "HÇ", "tur": "Galop"}], "REFLECTED GLORY": [{"t": "19.07.2026", "m1400": "", "m1200": "", "m1000": "", "m800": "0.53.80", "durum": "R", "tur": "Galop"}, {"t": "17.07.2026", "m1400": "", "m1200": "", "m1000": "", "m800": "", "durum": "R", "tur": "Sprint"}, {"t": "12.07.2026", "m1400": "", "m1200": "", "m1000": "", "m800": "0.53.30", "durum": "R", "tur": "Galop"}, {"t": "10.07.2026", "m1400": "", "m1200": "", "m1000": "", "m800": "", "durum": "R", "tur": "Sprint"}, {"t": "28.06.2026", "m1400": "", "m1200": "", "m1000": "", "m800": "0.52.20", "durum": "R", "tur": "Galop"}, {"t": "26.06.2026", "m1400": "", "m1200": "", "m1000": "", "m800": "", "durum": "R", "tur": "Galop"}], "RİBARO": [{"t": "03.04.2026", "m1400": "", "m1200": "", "m1000": "", "m800": "", "durum": "R", "tur": "Sprint"}, {"t": "18.07.2025", "m1400": "", "m1200": "", "m1000": "", "m800": "", "durum": "", "tur": "Kenter"}, {"t": "10.07.2025", "m1400": "", "m1200": "", "m1000": "", "m800": "", "durum": "R", "tur": "Sprint"}, {"t": "06.07.2025", "m1400": "", "m1200": "", "m1000": "", "m800": "", "durum": "R", "tur": "Galop"}, {"t": "24.06.2025", "m1400": "", "m1200": "", "m1000": "", "m800": "0.56.50", "durum": "HÇ", "tur": "Galop"}, {"t": "03.06.2025", "m1400": "", "m1200": "", "m1000": "", "m800": "0.57.20", "durum": "R", "tur": "Galop"}], "SAYRA": [{"t": "19.07.2026", "m1400": "", "m1200": "", "m1000": "", "m800": "0.56.40", "durum": "R", "tur": "Galop"}, {"t": "05.07.2026", "m1400": "", "m1200": "", "m1000": "", "m800": "0.56.50", "durum": "R", "tur": "Galop"}, {"t": "18.06.2026", "m1400": "", "m1200": "", "m1000": "", "m800": "", "durum": "R", "tur": "Sprint"}, {"t": "14.06.2026", "m1400": "", "m1200": "", "m1000": "", "m800": "0.56.20", "durum": "R", "tur": "Galop"}, {"t": "07.06.2026", "m1400": "", "m1200": "", "m1000": "", "m800": "0.58.30", "durum": "R", "tur": "Galop"}, {"t": "05.06.2026", "m1400": "", "m1200": "", "m1000": "", "m800": "", "durum": "R", "tur": "Sprint"}], "SECRET MAN": [{"t": "20.07.2026", "m1400": "", "m1200": "", "m1000": "", "m800": "0.56.70", "durum": "R", "tur": "Galop"}, {"t": "27.06.2026", "m1400": "", "m1200": "", "m1000": "", "m800": "0.55.00", "durum": "R", "tur": "Galop"}, {"t": "08.06.2026", "m1400": "", "m1200": "", "m1000": "", "m800": "", "durum": "R", "tur": "Galop"}, {"t": "16.05.2026", "m1400": "", "m1200": "", "m1000": "1.06.50", "m800": "", "durum": "R", "tur": "Galop"}, {"t": "09.05.2026", "m1400": "", "m1200": "1.18.00", "m1000": "1.05.00", "m800": "", "durum": "R", "tur": "Galop"}, {"t": "21.04.2026", "m1400": "", "m1200": "1.18.80", "m1000": "1.05.00", "m800": "", "durum": "R", "tur": "Galop"}], "SEQUOIA": [{"t": "12.07.2026", "m1400": "", "m1200": "", "m1000": "", "m800": "0.53.30", "durum": "R", "tur": "Galop"}, {"t": "20.06.2026", "m1400": "", "m1200": "", "m1000": "", "m800": "0.53.30", "durum": "R", "tur": "Galop"}, {"t": "06.06.2026", "m1400": "", "m1200": "", "m1000": "", "m800": "0.54.40", "durum": "R", "tur": "Galop"}, {"t": "10.05.2026", "m1400": "", "m1200": "", "m1000": "", "m800": "0.50.30", "durum": "R", "tur": "Galop"}, {"t": "07.05.2026", "m1400": "", "m1200": "", "m1000": "", "m800": "", "durum": "R", "tur": "Galop"}, {"t": "03.05.2026", "m1400": "", "m1200": "", "m1000": "", "m800": "0.53.20", "durum": "R", "tur": "Galop"}], "SILENT RUNNER": [{"t": "21.07.2026", "m1400": "", "m1200": "", "m1000": "", "m800": "", "durum": "R", "tur": "Sprint"}, {"t": "16.07.2026", "m1400": "", "m1200": "1.17.70", "m1000": "1.04.00", "m800": "", "durum": "R", "tur": "Galop"}, {"t": "12.07.2026", "m1400": "", "m1200": "", "m1000": "1.04.00", "m800": "", "durum": "R", "tur": "Galop"}, {"t": "09.07.2026", "m1400": "", "m1200": "", "m1000": "", "m800": "", "durum": "R", "tur": "Galop"}, {"t": "30.06.2026", "m1400": "", "m1200": "", "m1000": "", "m800": "", "durum": "R", "tur": "Galop"}, {"t": "26.06.2026", "m1400": "", "m1200": "", "m1000": "1.02.80", "m800": "", "durum": "R", "tur": "Galop"}], "TAKEOVER": [{"t": "17.07.2026", "m1400": "", "m1200": "1.19.30", "m1000": "1.05.30", "m800": "", "durum": "R", "tur": "Galop"}, {"t": "11.07.2026", "m1400": "", "m1200": "1.18.50", "m1000": "1.04.50", "m800": "", "durum": "R", "tur": "Galop"}, {"t": "09.07.2026", "m1400": "", "m1200": "", "m1000": "", "m800": "", "durum": "R", "tur": "Sprint"}, {"t": "05.07.2026", "m1400": "", "m1200": "", "m1000": "1.06.40", "m800": "", "durum": "R", "tur": "Galop"}, {"t": "27.06.2026", "m1400": "", "m1200": "", "m1000": "1.05.00", "m800": "", "durum": "R", "tur": "Galop"}, {"t": "21.06.2026", "m1400": "", "m1200": "", "m1000": "1.05.20", "m800": "", "durum": "R", "tur": "Galop"}], "THRACE FEVER": [{"t": "21.07.2026", "m1400": "", "m1200": "", "m1000": "", "m800": "", "durum": "R", "tur": "Sprint"}, {"t": "03.07.2026", "m1400": "", "m1200": "", "m1000": "", "m800": "", "durum": "R", "tur": "Galop"}, {"t": "18.06.2026", "m1400": "", "m1200": "", "m1000": "", "m800": "", "durum": "R", "tur": "Galop"}, {"t": "07.06.2026", "m1400": "", "m1200": "", "m1000": "", "m800": "0.52.00", "durum": "R", "tur": "Galop"}, {"t": "05.06.2026", "m1400": "", "m1200": "", "m1000": "", "m800": "", "durum": "R", "tur": "Galop"}, {"t": "22.05.2026", "m1400": "", "m1200": "", "m1000": "", "m800": "", "durum": "R", "tur": "Galop"}], "UĞURLU BEBEK": [{"t": "19.07.2026", "m1400": "", "m1200": "", "m1000": "", "m800": "0.57.00", "durum": "R", "tur": "Galop"}, {"t": "05.07.2026", "m1400": "", "m1200": "", "m1000": "", "m800": "0.58.60", "durum": "R", "tur": "Galop"}, {"t": "28.06.2026", "m1400": "", "m1200": "", "m1000": "", "m800": "0.57.00", "durum": "R", "tur": "Galop"}, {"t": "21.06.2026", "m1400": "", "m1200": "", "m1000": "", "m800": "0.57.00", "durum": "R", "tur": "Galop"}, {"t": "19.06.2026", "m1400": "", "m1200": "", "m1000": "", "m800": "", "durum": "R", "tur": "Sprint"}, {"t": "11.06.2026", "m1400": "", "m1200": "", "m1000": "", "m800": "", "durum": "R", "tur": "Galop"}], "VELOS THALOR": [{"t": "28.06.2026", "m1400": "", "m1200": "", "m1000": "", "m800": "0.49.50", "durum": "R", "tur": "Galop"}, {"t": "25.06.2026", "m1400": "", "m1200": "", "m1000": "", "m800": "", "durum": "R", "tur": "Galop"}, {"t": "21.06.2026", "m1400": "", "m1200": "", "m1000": "", "m800": "0.50.00", "durum": "R", "tur": "Galop"}, {"t": "06.06.2026", "m1400": "", "m1200": "", "m1000": "", "m800": "0.52.40", "durum": "HÇ", "tur": "Galop"}, {"t": "31.05.2026", "m1400": "", "m1200": "", "m1000": "1.08.00", "m800": "", "durum": "HÇ", "tur": "Galop"}, {"t": "29.05.2026", "m1400": "", "m1200": "", "m1000": "", "m800": "", "durum": "HÇ", "tur": "Sprint"}], "WOLF BROTHERS": [{"t": "20.07.2026", "m1400": "", "m1200": "", "m1000": "", "m800": "0.49.00", "durum": "R", "tur": "Galop"}, {"t": "18.07.2026", "m1400": "", "m1200": "", "m1000": "", "m800": "", "durum": "R", "tur": "Sprint"}, {"t": "15.06.2026", "m1400": "", "m1200": "", "m1000": "", "m800": "0.49.00", "durum": "R", "tur": "Galop"}, {"t": "08.06.2026", "m1400": "", "m1200": "", "m1000": "1.03.70", "m800": "", "durum": "R", "tur": "Galop"}, {"t": "01.06.2026", "m1400": "", "m1200": "1.17.00", "m1000": "1.04.60", "m800": "", "durum": "R", "tur": "Galop"}, {"t": "18.05.2026", "m1400": "", "m1200": "", "m1000": "", "m800": "0.49.60", "durum": "R", "tur": "Galop"}], "YURIBOYKA": [{"t": "19.07.2026", "m1400": "", "m1200": "", "m1000": "", "m800": "0.50.50", "durum": "R", "tur": "Galop"}, {"t": "17.07.2026", "m1400": "", "m1200": "", "m1000": "", "m800": "", "durum": "R", "tur": "Galop"}, {"t": "12.07.2026", "m1400": "", "m1200": "", "m1000": "", "m800": "0.49.90", "durum": "R", "tur": "Galop"}, {"t": "10.07.2026", "m1400": "", "m1200": "", "m1000": "", "m800": "", "durum": "R", "tur": "Galop"}, {"t": "03.07.2026", "m1400": "", "m1200": "", "m1000": "", "m800": "", "durum": "R", "tur": "Galop"}, {"t": "28.06.2026", "m1400": "", "m1200": "", "m1000": "1.04.50", "m800": "", "durum": "R", "tur": "Galop"}], "ZIBBOOSH": [{"t": "21.07.2026", "m1400": "", "m1200": "", "m1000": "", "m800": "", "durum": "R", "tur": "Sprint"}, {"t": "17.07.2026", "m1400": "", "m1200": "", "m1000": "1.04.00", "m800": "", "durum": "R", "tur": "Galop"}, {"t": "15.07.2026", "m1400": "", "m1200": "", "m1000": "", "m800": "", "durum": "R", "tur": "Galop"}, {"t": "22.06.2026", "m1400": "", "m1200": "", "m1000": "1.03.80", "m800": "", "durum": "R", "tur": "Galop"}, {"t": "06.06.2026", "m1400": "", "m1200": "", "m1000": "1.02.40", "m800": "", "durum": "HR", "tur": "Galop"}, {"t": "31.05.2026", "m1400": "", "m1200": "", "m1000": "", "m800": "0.50.20", "durum": "R", "tur": "Galop"}], "ÖZBEK PRENSESİ": [{"t": "21.07.2026", "m1400": "", "m1200": "", "m1000": "", "m800": "", "durum": "R", "tur": "Sprint"}, {"t": "17.07.2026", "m1400": "", "m1200": "", "m1000": "", "m800": "", "durum": "R", "tur": "Sprint"}, {"t": "30.05.2026", "m1400": "", "m1200": "", "m1000": "", "m800": "", "durum": "ÇR", "tur": "Galop"}, {"t": "26.05.2026", "m1400": "", "m1200": "", "m1000": "", "m800": "", "durum": "R", "tur": "Sprint"}, {"t": "16.05.2026", "m1400": "", "m1200": "", "m1000": "", "m800": "", "durum": "R", "tur": "Galop"}, {"t": "02.05.2026", "m1400": "", "m1200": "", "m1000": "", "m800": "", "durum": "R", "tur": "Galop"}], "ŞAHLANTAY": [{"t": "21.07.2026", "m1400": "", "m1200": "", "m1000": "", "m800": "", "durum": "R", "tur": "Sprint"}, {"t": "17.07.2026", "m1400": "", "m1200": "", "m1000": "1.11.00", "m800": "", "durum": "R", "tur": "Galop"}, {"t": "26.06.2026", "m1400": "", "m1200": "", "m1000": "", "m800": "0.55.00", "durum": "Ç", "tur": "Galop"}, {"t": "21.06.2026", "m1400": "", "m1200": "", "m1000": "", "m800": "", "durum": "R", "tur": "Galop"}, {"t": "11.06.2026", "m1400": "", "m1200": "", "m1000": "", "m800": "", "durum": "R", "tur": "Sprint"}, {"t": "07.06.2026", "m1400": "", "m1200": "1.25.50", "m1000": "1.10.70", "m800": "", "durum": "R", "tur": "Galop"}]}