{"NEVZAT AVCİ": {"kosu": 624, "p1": 144, "p2": 97, "p3": 93}, "VEDAT ABİŞ": {"kosu": 677, "p1": 144, "p2": 126, "p3": 102}, "MUHAMMED MİR BİLGİN": {"kosu": 739, "p1": 142, "p2": 117, "p3": 99}, "AYHAN KURŞUN": {"kosu": 611, "p1": 119, "p2": 86, "p3": 77}, "İSA AKYAVUZ": {"kosu": 479, "p1": 104, "p2": 86, "p3": 63}, "MEHMET SALİH ÇELİK": {"kosu": 575, "p1": 101, "p2": 90, "p3": 79}, "MEHMET KAYA": {"kosu": 568, "p1": 95, "p2": 85, "p3": 72}, "AHMET ÇELİK": {"kosu": 454, "p1": 92, "p2": 78, "p3": 64}, "ALİ YILDIZ": {"kosu": 696, "p1": 83, "p2": 110, "p3": 83}, "MÜSLÜM ÇELİK": {"kosu": 638, "p1": 81, "p2": 81, "p3": 88}, "MUSTAFA ÇİÇEK": {"kosu": 405, "p1": 75, "p2": 67, "p3": 44}, "ERCAN ÇANKAYA": {"kosu": 543, "p1": 72, "p2": 76, "p3": 82}, "HIŞMAN ÇİZİK": {"kosu": 492, "p1": 68, "p2": 60, "p3": 76}, "FERİT YARDIMCI": {"kosu": 274, "p1": 66, "p2": 44, "p3": 39}, "ÖMER FARUK ÖZEN(Y2)": {"kosu": 529, "p1": 63, "p2": 70, "p3": 60}, "GÖKHAN KOCAKAYA": {"kosu": 254, "p1": 59, "p2": 44, "p3": 37}, "ERAY ÇİZİK": {"kosu": 436, "p1": 58, "p2": 42, "p3": 62}, "HALİS KARATAŞ": {"kosu": 231, "p1": 57, "p2": 46, "p3": 26}, "ERTUĞRUL CANKILIÇ(Y2)": {"kosu": 411, "p1": 57, "p2": 48, "p3": 43}, "AKIN SÖZEN": {"kosu": 410, "p1": 51, "p2": 47, "p3": 63}, "SALİH ÇELİK": {"kosu": 511, "p1": 48, "p2": 48, "p3": 46}, "ÖZCAN YILDIRIM": {"kosu": 277, "p1": 46, "p2": 53, "p3": 35}, "ALİ MEHDİ ALTIN": {"kosu": 417, "p1": 46, "p2": 52, "p3": 54}, "NECMİ ALTIN": {"kosu": 427, "p1": 45, "p2": 51, "p3": 57}, "BEKİR MERT MIRIK": {"kosu": 380, "p1": 44, "p2": 38, "p3": 47}, "AZİZ AKDEMİR": {"kosu": 385, "p1": 42, "p2": 37, "p3": 41}, "YİĞİTCAN GÖKÇE(Y2)": {"kosu": 450, "p1": 42, "p2": 49, "p3": 44}, "ONUR YILDIZ": {"kosu": 278, "p1": 40, "p2": 41, "p3": 35}, "MEHMET AKYAVUZ": {"kosu": 333, "p1": 40, "p2": 41, "p3": 44}, "ERHAN AKTUĞ": {"kosu": 473, "p1": 38, "p2": 33, "p3": 42}, "MEHMET ALİ AKGÖBEK": {"kosu": 486, "p1": 37, "p2": 33, "p3": 47}, "MURAT KEÇECİ": {"kosu": 469, "p1": 37, "p2": 43, "p3": 40}, "SELİM KAYA": {"kosu": 133, "p1": 34, "p2": 25, "p3": 11}, "GÖRKEM ÖZÇELİK": {"kosu": 485, "p1": 34, "p2": 57, "p3": 55}, "İSA KATAR": {"kosu": 386, "p1": 33, "p2": 39, "p3": 44}, "AHMET HASAN BAYAR": {"kosu": 344, "p1": 31, "p2": 39, "p3": 34}, "YUSUF CENGİZ": {"kosu": 414, "p1": 30, "p2": 39, "p3": 37}, "RECEP KETME(Y1)": {"kosu": 405, "p1": 30, "p2": 36, "p3": 40}, "NİZAMETTİN DEMİR": {"kosu": 428, "p1": 30, "p2": 37, "p3": 43}, "MERT ALİ SOLMAZ": {"kosu": 232, "p1": 26, "p2": 31, "p3": 22}, "ONUR ATMACA": {"kosu": 410, "p1": 25, "p2": 31, "p3": 44}, "GÖKHAN GÖKÇE": {"kosu": 161, "p1": 23, "p2": 16, "p3": 30}, "ENES BOZDAĞ": {"kosu": 242, "p1": 23, "p2": 15, "p3": 22}, "KADİR TOKAÇOĞLU": {"kosu": 241, "p1": 22, "p2": 34, "p3": 24}, "MAHSUN TURAN": {"kosu": 144, "p1": 21, "p2": 12, "p3": 11}, "ALİ KAÇMAZ": {"kosu": 234, "p1": 21, "p2": 27, "p3": 26}, "EFE AKPINAR(Y1)": {"kosu": 204, "p1": 20, "p2": 16, "p3": 21}, "HASAN ALTUNDAĞ": {"kosu": 250, "p1": 20, "p2": 20, "p3": 23}, "ALİCAN İNCİ": {"kosu": 282, "p1": 20, "p2": 16, "p3": 43}, "MEHMET TAŞKAYA": {"kosu": 74, "p1": 17, "p2": 9, "p3": 4}}