{
 "date": "2026-07-21",
 "city": "Kocaeli",
 "isResult": false,
 "races": [
  {
   "no": 1,
   "saat": "17.45",
   "tur": "SATIŞ 1",
   "grup": "3 ve Yukarı İngilizler",
   "kilo": "54.00kg",
   "mesafe": "2000m",
   "pist": "Kum",
   "horses": [
    {
     "no": 1,
     "ad": "SÖNMEZ YİĞİT KG DB SK",
     "yas": "6y a  a",
     "baba": "KANEKO",
     "anne": "SHANTI (GER)",
     "kilo": "60,5",
     "jokey": "K.TOKAÇOĞLU",
     "sahip": "MURAT SÖNMEZ",
     "antrenor": "R.KARABULUT",
     "st": "5",
     "agf": "%9.42(5)",
     "h": "88",
     "son6": "K1K0-K0K2K4K6",
     "kgs": "67",
     "s20": "15",
     "eniyi": "2:11.04"
    },
    {
     "no": 2,
     "ad": "GRAND MISSION KG DB",
     "yas": "7y d  a",
     "baba": "JIMMY CREED (USA)",
     "anne": "FINANCIAL CRISIS (USA)",
     "kilo": "59,5",
     "jokey": "M.ÇİÇEK",
     "sahip": "LÜTFİ TURAN",
     "antrenor": "M.U.TURAN",
     "st": "7",
     "agf": "%19.51(2)",
     "h": "85",
     "son6": "K4K1Ç7K4K3K4",
     "kgs": "29",
     "s20": "20",
     "eniyi": "2:07.86"
    },
    {
     "no": 3,
     "ad": "KING OF THE NIGHT SK",
     "yas": "7y a  a",
     "baba": "PACO BOY (IRE)",
     "anne": "NURMAHAL",
     "kilo": "59,5",
     "jokey": "BERK.GÖKÇE AP",
     "sahip": "SERDAR PEKİN",
     "antrenor": "M.AKKILIÇ",
     "st": "4",
     "agf": "%10.18(4)",
     "h": "81",
     "son6": "K3K3K5K4K4K4",
     "kgs": "8",
     "s20": "17",
     "eniyi": "2:09.63"
    },
    {
     "no": 4,
     "ad": "BY TÜRE K DB",
     "yas": "4y d  a",
     "baba": "CORINTHIAN (USA)",
     "anne": "ALHİLAL",
     "kilo": "58",
     "jokey": "M.M.BİLGİN",
     "sahip": "HAKAN CANTINAZ",
     "antrenor": "HAK.POLAT",
     "st": "9 - DS",
     "agf": "%10.37(3)",
     "h": "68",
     "son6": "K1-K3K0K3K1K0",
     "kgs": "91",
     "s20": "19",
     "eniyi": "2:09.50"
    },
    {
     "no": 5,
     "ad": "AFTER YOU KG SK",
     "yas": "4y d  a",
     "baba": "DAI JIN (GB)",
     "anne": "URFAGÜLÜ",
     "kilo": "57",
     "jokey": "M.A.AKGÖBEK",
     "sahip": "YÜKSEL TEKİNALP",
     "antrenor": "K.TEKİNALP",
     "st": "2",
     "agf": "%5.77(8)",
     "h": "73",
     "son6": "K6-K2Ç0K4K6K4",
     "kgs": "17",
     "s20": "14",
     "eniyi": "2:12.13"
    },
    {
     "no": 6,
     "ad": "LION PEKAN DB SKG SK",
     "yas": "5y d  a",
     "baba": "TIZWAY (USA)",
     "anne": "YASEMİN KIZ",
     "kilo": "56,5",
     "jokey": "N.AVCİ",
     "sahip": "MUZAFFER TEZER",
     "antrenor": "R.SUNA",
     "st": "8 - DS",
     "agf": "%8.23(7)",
     "h": "88",
     "son6": "K9K2K4K6K8K7",
     "kgs": "5",
     "s20": "13",
     "eniyi": "2:10.35"
    },
    {
     "no": 7,
     "ad": "RÜZGAR UĞUR DB SK",
     "yas": "6y a  a",
     "baba": "SIDNEY'S CANDY (USA)",
     "anne": "PASİFİKA",
     "kilo": "55,5",
     "jokey": "G.ÖZÇELİK",
     "sahip": "MEHMET ÇELİK",
     "antrenor": "M.DAŞ",
     "st": "3",
     "agf": "%8.73(6)",
     "h": "80",
     "son6": "K1-K9Ç6K7K6K9",
     "kgs": "21",
     "s20": "15",
     "eniyi": "2:11.03"
    },
    {
     "no": 8,
     "ad": "STEEL FATHER KG K DB",
     "yas": "3y d  e",
     "baba": "LION HEART (USA)",
     "anne": "LADY AKARCA",
     "kilo": "54",
     "jokey": "MAH.TURAN",
     "sahip": "NAFİZ ÇELİK",
     "antrenor": "Ö.F.TAŞDELEN",
     "st": "1",
     "agf": "%25.68(1)",
     "h": "59",
     "son6": "K1K2K5K3K5K2",
     "kgs": "14",
     "s20": "17",
     "eniyi": "2:12.48"
    },
    {
     "no": 9,
     "ad": "SİYAH KRAL K SKG",
     "yas": "4y k  a",
     "baba": "AGRESIVO (USA)",
     "anne": "DİRHEM DİRHEM",
     "kilo": "55",
     "jokey": "O.ATMACA",
     "sahip": "ZEYNEP CEYLAN",
     "antrenor": "M.ALTIN",
     "st": "6",
     "agf": "%2.12(9)",
     "h": "27",
     "son6": "K0K7K4K8K4K0",
     "kgs": "23",
     "s20": "5",
     "eniyi": "2:12.88"
    }
   ],
   "ikramiye": "385.000 TL"
  },
  {
   "no": 2,
   "saat": "18.30",
   "tur": "ŞARTLI 3",
   "grup": "3 Yaşlı İngilizler",
   "kilo": "58.00kg",
   "mesafe": "1500m",
   "pist": "Kum",
   "horses": [
    {
     "no": 1,
     "ad": "AL SAROUT KG K DB",
     "yas": "3y d  e",
     "baba": "MENDIP (USA)",
     "anne": "ARBAAH (USA)",
     "kilo": "58",
     "jokey": "A.SÖZEN",
     "sahip": "SOLAIMAN IRHAIM",
     "antrenor": "Y.ARHIM",
     "st": "5",
     "agf": "%52.19(1)",
     "h": "58",
     "son6": "K1K2-K1K2K3",
     "kgs": "14",
     "s20": "18",
     "eniyi": "1:34.61"
    },
    {
     "no": 2,
     "ad": "STORMER KG DB SK SGKR",
     "yas": "3y d  e",
     "baba": "KANEKO",
     "anne": "HESKIN (IRE)",
     "kilo": "58",
     "jokey": "S.ÖZEN",
     "sahip": "ERGUN KALABAK",
     "antrenor": "E.KARACA",
     "st": "6",
     "agf": "%6.07(6)",
     "h": "42",
     "son6": "Ç3Ç1Ç7Ç0",
     "kgs": "36",
     "s20": "18",
     "eniyi": ""
    },
    {
     "no": 3,
     "ad": "WARRIOR MAN DB SK",
     "yas": "3y d  e",
     "baba": "SUPER SAVER (USA)",
     "anne": "FAIR STORM",
     "kilo": "58",
     "jokey": "M.ÇİÇEK",
     "sahip": "İBRAHİM HALİL YILDIZSOY",
     "antrenor": "H.DOLMAZ",
     "st": "4",
     "agf": "%12.16(2)",
     "h": "54",
     "son6": "K1K4Ç0K2K3K5",
     "kgs": "5",
     "s20": "16",
     "eniyi": "1:36.82"
    },
    {
     "no": 4,
     "ad": "HAMMERWICH DB SKG SK",
     "yas": "3y d  d",
     "baba": "PAPA CLEM (USA)",
     "anne": "JUNAMAXIMA",
     "kilo": "56",
     "jokey": "M.M.BİLGİN",
     "sahip": "FARUK AY",
     "antrenor": "GAL.KILIÇ",
     "st": "1",
     "agf": "%10.57(3)",
     "h": "46",
     "son6": "K4K9K4K0K7K1",
     "kgs": "14",
     "s20": "20",
     "eniyi": "1:35.90"
    },
    {
     "no": 5,
     "ad": "VICTORY STAR SKG SK",
     "yas": "3y d  d",
     "baba": "LION HEART (USA)",
     "anne": "VIRGIN PEARL (USA)",
     "kilo": "56",
     "jokey": "G.ÖZÇELİK",
     "sahip": "MAHMUT YARDIMCI",
     "antrenor": "H.DOLMAZ",
     "st": "3",
     "agf": "%6.88(5)",
     "h": "63",
     "son6": "K2K8K6K4K7K5",
     "kgs": "12",
     "s20": "13",
     "eniyi": "1:34.48"
    },
    {
     "no": 6,
     "ad": "IRON CLEM DB SK",
     "yas": "3y d  g",
     "baba": "PAPA CLEM (USA)",
     "anne": "DEMİRSU",
     "kilo": "55",
     "jokey": "B.AKÇAY",
     "sahip": "İLHAN KAPUSIZ",
     "antrenor": "E.USLU",
     "st": "8",
     "agf": "%1.92(8)",
     "h": "44",
     "son6": "S3S5Ç8S7K9S0",
     "kgs": "9",
     "s20": "9",
     "eniyi": ""
    },
    {
     "no": 7,
     "ad": "BLUE STAR KG K DB GKR",
     "yas": "3y d  e",
     "baba": "BLUEGRASS CAT (USA)",
     "anne": "YILDIZ AYAK",
     "kilo": "58",
     "jokey": "A.YILDIZ",
     "sahip": "KEMAL A. TURAN",
     "antrenor": "HÜS.ÇAKMAK",
     "st": "2",
     "agf": "%7.7(4)",
     "h": "39",
     "son6": "Ç4-S0Ç0K1",
     "kgs": "33",
     "s20": "20",
     "eniyi": ""
    },
    {
     "no": 8,
     "ad": "ANSHBA FOREVER",
     "yas": "3y d  e",
     "baba": "BODEMEISTER (USA)",
     "anne": "WELLDONES DAUGHTER",
     "kilo": "52",
     "jokey": "Y.GÖKÇE AP",
     "sahip": "Y.ERKUT ERSEVER",
     "antrenor": "C.TURAN",
     "st": "7",
     "agf": "%2.52(7)",
     "h": "",
     "son6": "S8S8",
     "kgs": "321",
     "s20": "18",
     "eniyi": ""
    }
   ],
   "ikramiye": "400.000 TL"
  },
  {
   "no": 3,
   "saat": "19.00",
   "tur": "Maiden",
   "grup": "2 Yaşlı İngilizler",
   "kilo": "57.00kg",
   "mesafe": "1200m",
   "pist": "Kum",
   "horses": [
    {
     "no": 1,
     "ad": "SUPER LION KG K DB",
     "yas": "2y d  e",
     "baba": "HEP BERABER",
     "anne": "BOSENDRA",
     "kilo": "60",
     "jokey": "MAH.TURAN",
     "sahip": "SELİLE ELĞAÇ",
     "antrenor": "S.GÜNAYDIN",
     "st": "5",
     "agf": "%38.92(1)  %33.43(1)",
     "h": "34",
     "son6": "Ç2Ç3Ç4K3K2",
     "kgs": "7",
     "s20": "17",
     "eniyi": "1:16.83"
    },
    {
     "no": 2,
     "ad": "TEMERARIO SK",
     "yas": "2y d  e",
     "baba": "BODEMEISTER (USA)",
     "anne": "COCONUT",
     "kilo": "58",
     "jokey": "Y.GÖKÇE AP",
     "sahip": "MEHMET ALİ KATI",
     "antrenor": "H.SUNKAR",
     "st": "9 - DS",
     "agf": "%5.49(6)  %3.4(6)",
     "h": "29",
     "son6": "K4K4K4K4K5K5",
     "kgs": "10",
     "s20": "17",
     "eniyi": "1:18.19"
    },
    {
     "no": 3,
     "ad": "BAŞIMIN BELASI KG K",
     "yas": "2y d  e",
     "baba": "MYBOYCHARLIE (IRE)",
     "anne": "GREEN PEARL",
     "kilo": "57",
     "jokey": "M.A.AKGÖBEK",
     "sahip": "YILMAZ TEKİNALP",
     "antrenor": "M.ALTIN",
     "st": "6",
     "agf": "%2.37(9)  %1.96(8)",
     "h": "",
     "son6": "K8",
     "kgs": "12",
     "s20": "19",
     "eniyi": "1:21.11"
    },
    {
     "no": 4,
     "ad": "KOCA ÖMER KG SK",
     "yas": "2y d  e",
     "baba": "AZARAKS",
     "anne": "TURF QUEEN",
     "kilo": "57",
     "jokey": "B.AKÇAY",
     "sahip": "EMRE KOCAMAN",
     "antrenor": "T.ATAÇ",
     "st": "3",
     "agf": "%7.23(5)  %8.88(4)",
     "h": "",
     "son6": "K3",
     "kgs": "12",
     "s20": "19",
     "eniyi": "1:19.29"
    },
    {
     "no": 5,
     "ad": "ONUR BEYİM KG",
     "yas": "2y a  e",
     "baba": "GRAYSTORM",
     "anne": "MAYA KISKA",
     "kilo": "57",
     "jokey": "A.YILDIZ",
     "sahip": "ONUR GENÇER",
     "antrenor": "N.GENÇER",
     "st": "7",
     "agf": "%20.53(2)  %26.34(2)",
     "h": "32",
     "son6": "K5K4K2",
     "kgs": "19",
     "s20": "17",
     "eniyi": "1:18.40"
    },
    {
     "no": 6,
     "ad": "TALLIN",
     "yas": "2y d  e",
     "baba": "BODYGUARD HERO (USA)",
     "anne": "SULTAN REEDS",
     "kilo": "57",
     "jokey": "S.ÖZEN",
     "sahip": "FEDAİ KAHRAMAN",
     "antrenor": "Ö.F.TAŞDELEN",
     "st": "4",
     "agf": "%11.85(3)  %14.07(3)",
     "h": "",
     "son6": "K4",
     "kgs": "12",
     "s20": "19",
     "eniyi": "1:19.06"
    },
    {
     "no": 7,
     "ad": "BİLGÜCÜ DB SK",
     "yas": "2y d  d",
     "baba": "TRAPPE SHOT (USA)",
     "anne": "GÜZELKÖYLÜ",
     "kilo": "52",
     "jokey": "Ö.F.ÖZEN AP",
     "sahip": "MURAT ÇELİK",
     "antrenor": "Y.ÖZTAŞ",
     "st": "8",
     "agf": "%2.48(8)  %1.67(9)",
     "h": "",
     "son6": "Ç9",
     "kgs": "15",
     "s20": "19",
     "eniyi": ""
    },
    {
     "no": 8,
     "ad": "EYLÜL MASALI SK",
     "yas": "2y d  d",
     "baba": "HAKEEM (USA)",
     "anne": "RİTİM",
     "kilo": "55",
     "jokey": "O.ATMACA",
     "sahip": "İLKE BETİR AKBAŞ",
     "antrenor": "K.ŞENGEL",
     "st": "2",
     "agf": "%2.87(7)  %2(7)",
     "h": "",
     "son6": "Ç9",
     "kgs": "15",
     "s20": "19",
     "eniyi": ""
    },
    {
     "no": 9,
     "ad": "WHITE WRIST KG DB SK",
     "yas": "2y d  d",
     "baba": "TRAPPE SHOT (USA)",
     "anne": "EUCLASE (USA)",
     "kilo": "55",
     "jokey": "F.S.M.SANSAR",
     "sahip": "SIRAÇ DEMİR",
     "antrenor": "F.DEMİR",
     "st": "1",
     "agf": "%8.26(4)  %8.25(5)",
     "h": "30",
     "son6": "Ç7K7K3K2Ç8K4",
     "kgs": "22",
     "s20": "14",
     "eniyi": "1:17.24"
    }
   ],
   "ikramiye": "545.000 TL"
  },
  {
   "no": 4,
   "saat": "19.30",
   "tur": "Handikap 15 /H2",
   "grup": "3 ve Yukarı İngilizler",
   "kilo": "kg",
   "mesafe": "1800m",
   "pist": "Kum",
   "horses": [
    {
     "no": 1,
     "ad": "BIG GAMBLE KG DB SK",
     "yas": "6y d  a",
     "baba": "MALİ",
     "anne": "CHERRY LADY",
     "kilo": "63",
     "jokey": "S.ÖZEN",
     "sahip": "ORHAN BAŞPINAR",
     "antrenor": "H.ŞİMŞEK",
     "st": "2",
     "agf": "%5.45(7)  %2.54(8)",
     "h": "53",
     "son6": "K5K3K3S5K0K9",
     "kgs": "91",
     "s20": "15",
     "eniyi": ""
    },
    {
     "no": 2,
     "ad": "FORTUNELLO SKG SK",
     "yas": "7y d  a",
     "baba": "SMART ROBIN (JPN)",
     "anne": "SPIRA (IRE)",
     "kilo": "60",
     "jokey": "S.ÇELİK AP",
     "sahip": "SELİN DİKENCİK",
     "antrenor": "M.ÖZGÜL",
     "st": "1",
     "agf": "%8.53(4)  %8.44(4)",
     "h": "53",
     "son6": "K6K6K7K5K7K6",
     "kgs": "8",
     "s20": "10",
     "eniyi": "1:57.50"
    },
    {
     "no": 3,
     "ad": "MONUMENTAL KG DB SK",
     "yas": "4y d  a",
     "baba": "MYBOYCHARLIE (IRE)",
     "anne": "PIN UP",
     "kilo": "60",
     "jokey": "E.AKPINAR AP",
     "sahip": "RECEP AVŞAR",
     "antrenor": "HÜS.KARABULUT",
     "st": "3",
     "agf": "%11.09(2)  %9.68(3)",
     "h": "53",
     "son6": "K3K2K5K8K5K9",
     "kgs": "15",
     "s20": "15",
     "eniyi": "1:56.94"
    },
    {
     "no": 4,
     "ad": "MAKE FUN OF DB SK",
     "yas": "3y d  e",
     "baba": "KLIMT (USA)",
     "anne": "FULLMOON",
     "kilo": "56,5",
     "jokey": "F.S.M.SANSAR",
     "sahip": "EMRE AKIN",
     "antrenor": "H.KABUKCI",
     "st": "7",
     "agf": "%41.46(1)  %40.96(1)",
     "h": "51",
     "son6": "K3K4K2K1K1K3",
     "kgs": "15",
     "s20": "19",
     "eniyi": "1:57.02"
    },
    {
     "no": 5,
     "ad": "Mİ PRİNCESA ŞÜKRAN KG DB SK",
     "yas": "5y d k",
     "baba": "TRAPPE SHOT (USA)",
     "anne": "HEAVEN'S HELP (USA)",
     "kilo": "58",
     "jokey": "Y.GÖKÇE AP",
     "sahip": "EMRE AKIN",
     "antrenor": "H.KABUKCI",
     "st": "8",
     "agf": "%3.75(1)  %3.87(1)",
     "h": "47",
     "son6": "K2K3K6K4K6K7",
     "kgs": "33",
     "s20": "14",
     "eniyi": "1:57.25"
    },
    {
     "no": 6,
     "ad": "ALASER K",
     "yas": "4y d  a",
     "baba": "KLUGER (JPN)",
     "anne": "RIVER OF LOVE",
     "kilo": "58",
     "jokey": "M.M.BİLGİN",
     "sahip": "MAZLUM TURAN",
     "antrenor": "TU.TURAN",
     "st": "4",
     "agf": "%8.09(5)  %6.01(6)",
     "h": "43",
     "son6": "Ç0Ç0Ç7K5K0K7",
     "kgs": "7",
     "s20": "7",
     "eniyi": ""
    },
    {
     "no": 7,
     "ad": "VENUS DOOM KG DB SK",
     "yas": "3y a  e",
     "baba": "TRAPPE SHOT (USA)",
     "anne": "GLASS PATH (USA)",
     "kilo": "52",
     "jokey": "B.AKÇAY",
     "sahip": "AHMET VOLKAN SÜNTER",
     "antrenor": "E.USLU",
     "st": "6",
     "agf": "%9.45(3)  %15.8(2)",
     "h": "41",
     "son6": "S5K1K5-K3S7K4",
     "kgs": "91",
     "s20": "16",
     "eniyi": ""
    },
    {
     "no": 8,
     "ad": "KUMKAPILI KG SK",
     "yas": "5y d  a",
     "baba": "TONY MONTANA",
     "anne": "CANPARE",
     "kilo": "56",
     "jokey": "A.YILDIZ",
     "sahip": "KAMİL ARDA",
     "antrenor": "Ş.GÖKÇE",
     "st": "5",
     "agf": "%7.5(6)  %8.3(5)",
     "h": "39",
     "son6": "K3Ç9S6K3K2-K0",
     "kgs": "33",
     "s20": "14",
     "eniyi": ""
    },
    {
     "no": 9,
     "ad": "KATANA BOY KG DB SK",
     "yas": "4y a  a",
     "baba": "LION HEART (USA)",
     "anne": "PEACE TRAIL",
     "kilo": "53,5",
     "jokey": "C.TEPE",
     "sahip": "İBRAHİM YILDIZ",
     "antrenor": "HÜS.KARABULUT",
     "st": "9",
     "agf": "%4.67(8)  %4.41(7)",
     "h": "34",
     "son6": "K5K7Ç7K4K5K5",
     "kgs": "7",
     "s20": "15",
     "eniyi": ""
    }
   ],
   "ikramiye": "490.000 TL"
  },
  {
   "no": 5,
   "saat": "20.00",
   "tur": "KV-6/DHÖW",
   "grup": "3 Yaşlı Araplar",
   "kilo": "57.00kg",
   "mesafe": "1200m",
   "pist": "Kum",
   "horses": [
    {
     "no": 1,
     "ad": "GUREGH KG K DB GKR",
     "yas": "3y k  e",
     "baba": "KAYAYÜREKLİ",
     "anne": "SABIRLIKAYA",
     "kilo": "57",
     "jokey": "N.AVCİ",
     "sahip": "AZİZE KAYA",
     "antrenor": "M.DEMİRTAŞ",
     "st": "4",
     "agf": "%14.31(3)  %15.83(2)",
     "h": "49",
     "son6": "Ç2S8Ç5K1K1K2",
     "kgs": "10",
     "s20": "19",
     "eniyi": "1:23.31"
    },
    {
     "no": 2,
     "ad": "GÜMBÜR BABA SK",
     "yas": "3y a  e",
     "baba": "GÜMBÜRGÜMBÜR",
     "anne": "HAREM",
     "kilo": "57",
     "jokey": "A.MEH.ALTIN",
     "sahip": "ÖMER FARUK ALTIN",
     "antrenor": "M.ALTIN",
     "st": "7",
     "agf": "%21.33(2)  %22.42(1)",
     "h": "52",
     "son6": "K1K4K3K2K1",
     "kgs": "24",
     "s20": "20",
     "eniyi": "1:22.22"
    },
    {
     "no": 3,
     "ad": "SALGUR KG SK",
     "yas": "3y k  e",
     "baba": "KURTÇABEY",
     "anne": "NEVRAZİN",
     "kilo": "57",
     "jokey": "M.A.AKGÖBEK",
     "sahip": "EKREM BİRDEN",
     "antrenor": "M.A.KAYA",
     "st": "8",
     "agf": "%10.26(4)  %9.63(5)",
     "h": "50",
     "son6": "K3S4K1K2K3K3",
     "kgs": "10",
     "s20": "17",
     "eniyi": "1:23.68"
    },
    {
     "no": 4,
     "ad": "CİHANERK KG DB SK",
     "yas": "3y k  e",
     "baba": "EMBİR HAN",
     "anne": "UÇANHAN",
     "kilo": "55",
     "jokey": "M.M.BİLGİN",
     "sahip": "EBRU KARGIN",
     "antrenor": "MUR.AKKILIÇ",
     "st": "9",
     "agf": "%7.52(7)  %8.89(7)",
     "h": "46",
     "son6": "S6Ç3S3S1S2Ç0",
     "kgs": "18",
     "s20": "18",
     "eniyi": ""
    },
    {
     "no": 5,
     "ad": "STARŞAH KG K",
     "yas": "3y k  e",
     "baba": "BİLDENHAN",
     "anne": "CEĞİTLİ",
     "kilo": "55",
     "jokey": "MAH.TURAN",
     "sahip": "MEHMET SALİH ELĞAÇ",
     "antrenor": "GAL.KILIÇ",
     "st": "5",
     "agf": "%21.51(1)  %15.83(3)",
     "h": "43",
     "son6": "K3K1K2K1S3K4",
     "kgs": "8",
     "s20": "18",
     "eniyi": "1:22.95"
    },
    {
     "no": 6,
     "ad": "BEGİHAN KG DB SK",
     "yas": "3y a  e",
     "baba": "YILMABAŞAR",
     "anne": "NEDİMEM",
     "kilo": "54",
     "jokey": "A.SÖZEN",
     "sahip": "AİT ÇELİK",
     "antrenor": "M.DAŞ",
     "st": "3",
     "agf": "%8.66(6)  %9.92(4)",
     "h": "40",
     "son6": "K3Ç4K3K1",
     "kgs": "14",
     "s20": "20",
     "eniyi": ""
    },
    {
     "no": 7,
     "ad": "DEVRAN BEY SK",
     "yas": "3y a  e",
     "baba": "ŞÜKRÜ",
     "anne": "HURNCANE",
     "kilo": "54",
     "jokey": "G.ÖZÇELİK",
     "sahip": "MERAL ÖZKAN",
     "antrenor": "D.SAV",
     "st": "6",
     "agf": "%9.43(5)  %9.39(6)",
     "h": "43",
     "son6": "K8K1K2",
     "kgs": "19",
     "s20": "19",
     "eniyi": "1:24.94"
    },
    {
     "no": 8,
     "ad": "PAPETTİ KG K",
     "yas": "3y a  e",
     "baba": "THOR",
     "anne": "ZELİHA HATUN",
     "kilo": "54",
     "jokey": "Ö.F.ÖZEN AP",
     "sahip": "KÜRŞAT ORUÇ",
     "antrenor": "GAL.KILIÇ",
     "st": "1",
     "agf": "%3.14(8)  %3.57(8)",
     "h": "36",
     "son6": "K2K1K4K3S5K3",
     "kgs": "19",
     "s20": "17",
     "eniyi": "1:25.25"
    },
    {
     "no": 9,
     "ad": "BEKATA KG K DB GKR",
     "yas": "3y a  e",
     "baba": "ORÇUN",
     "anne": "ŞAHANE KRALİÇE",
     "kilo": "53",
     "jokey": "A.ASLAN",
     "sahip": "GÜROL ULUDAĞ",
     "antrenor": "HÜS.KARABULUT",
     "st": "10 - DS",
     "agf": "%1.31(10)  %1.3(10)",
     "h": "30",
     "son6": "K3K2K4K4K0",
     "kgs": "14",
     "s20": "16",
     "eniyi": "1:25.71"
    },
    {
     "no": 10,
     "ad": "ŞENERHAN KG SK",
     "yas": "3y k  e",
     "baba": "FATİH AĞA",
     "anne": "ARTUNYILDIZI",
     "kilo": "53",
     "jokey": "A.YILDIZ",
     "sahip": "MEHMET YILDIRIM",
     "antrenor": "TU.TURAN",
     "st": "2",
     "agf": "%2.53(9)  %3.23(9)",
     "h": "41",
     "son6": "K1S4K5Ç5K5",
     "kgs": "19",
     "s20": "17",
     "eniyi": "1:23.95"
    }
   ],
   "ikramiye": "695.000 TL"
  },
  {
   "no": 6,
   "saat": "20.30",
   "tur": "Handikap 16/DHÖW /H2",
   "grup": "4 Yaşlı Araplar",
   "kilo": "kg",
   "mesafe": "2000m",
   "pist": "Kum",
   "horses": [
    {
     "no": 1,
     "ad": "SONYEL KG SK",
     "yas": "4y d  a",
     "baba": "SONALP",
     "anne": "SÜBEYHİKIZI",
     "kilo": "58,5",
     "jokey": "M.ÇELİK AP",
     "sahip": "MEHMET YILDIZ",
     "antrenor": "Ö.F.TAŞDELEN",
     "st": "6",
     "agf": "%15.31(2)  %16.35(2)",
     "h": "67",
     "son6": "K0-S0K5K1K3K1",
     "kgs": "12",
     "s20": "20",
     "eniyi": ""
    },
    {
     "no": 2,
     "ad": "KARSAVURANLI KG DB SK",
     "yas": "4y d  a",
     "baba": "ÖZHABER",
     "anne": "BALBADEMİM",
     "kilo": "58",
     "jokey": "BERK.GÖKÇE AP",
     "sahip": "VEHBİ ATEŞ",
     "antrenor": "M.A.CANPOLATLI",
     "st": "1",
     "agf": "%9.51(6)  %9.5(5)",
     "h": "64",
     "son6": "K1K4K2K2K1K6",
     "kgs": "14",
     "s20": "19",
     "eniyi": "2:25.84"
    },
    {
     "no": 3,
     "ad": "SAMET EFENDİ KG DB SK",
     "yas": "4y k  a",
     "baba": "MENGÜBERT",
     "anne": "SARIGOBAK",
     "kilo": "58,5",
     "jokey": "MAH.TURAN",
     "sahip": "ÜMİT YAĞMUR",
     "antrenor": "ADN.POLAT",
     "st": "3",
     "agf": "%14.62(3)  %6.32(6)",
     "h": "61",
     "son6": "K1K1K6K7K4Ç7",
     "kgs": "24",
     "s20": "16",
     "eniyi": ""
    },
    {
     "no": 4,
     "ad": "KAZDAĞI EFESİ",
     "yas": "4y a  a",
     "baba": "GÜMBÜRGÜMBÜR",
     "anne": "KAZDAĞI GÜZELİ",
     "kilo": "58,5",
     "jokey": "O.ATMACA",
     "sahip": "AHMET FAYDALGEL",
     "antrenor": "T.ÇEKİCİ",
     "st": "5",
     "agf": "%12.8(4)  %14.94(3)",
     "h": "61",
     "son6": "K5K3K1K1K5K2",
     "kgs": "7",
     "s20": "18",
     "eniyi": "2:27.72"
    },
    {
     "no": 5,
     "ad": "BAY OLOF KG SK",
     "yas": "4y a  a",
     "baba": "HABERKAN",
     "anne": "AYBURAK SULTAN",
     "kilo": "56,5",
     "jokey": "M.M.BİLGİN",
     "sahip": "FİKRET KANMAN",
     "antrenor": "Ş.Ş.DEMİR",
     "st": "7",
     "agf": "%11.33(5)  %13.35(4)",
     "h": "57",
     "son6": "K2K8S0Ç0K0K1",
     "kgs": "14",
     "s20": "20",
     "eniyi": ""
    },
    {
     "no": 6,
     "ad": "KESTENOĞLU KG DB SK",
     "yas": "4y a  a",
     "baba": "SERDÜMEN",
     "anne": "SEVDALIMSINCAN",
     "kilo": "56",
     "jokey": "N.AVCİ",
     "sahip": "MELTEM PALIT",
     "antrenor": "Y.TAŞKIN",
     "st": "2",
     "agf": "%29.43(1)  %33.7(1)",
     "h": "56",
     "son6": "K4K3Ç5S4K1K1",
     "kgs": "11",
     "s20": "20",
     "eniyi": "2:22.28"
    },
    {
     "no": 7,
     "ad": "TANJU BEY KG DB SK",
     "yas": "4y k  a",
     "baba": "TAMERİNOĞLU",
     "anne": "BEYAZ ALTIN",
     "kilo": "52",
     "jokey": "Y.Ş.GÜMÜŞ AP",
     "sahip": "M.LEVENT TOPSAKAL",
     "antrenor": "MİR.İPEK",
     "st": "4",
     "agf": "%7(7)  %5.85(7)",
     "h": "47",
     "son6": "K8K6K7S8K1K3",
     "kgs": "14",
     "s20": "19",
     "eniyi": "2:26.92"
    }
   ],
   "ikramiye": "630.000 TL"
  },
  {
   "no": 7,
   "saat": "21.00",
   "tur": "Handikap 16/Dişi /H2",
   "grup": "3 Yaşlı İngilizler",
   "kilo": "kg",
   "mesafe": "1700m",
   "pist": "Kum",
   "horses": [
    {
     "no": 1,
     "ad": "HEARTS PATH DB SKG SK",
     "yas": "3y d  d",
     "baba": "KLIMT (USA)",
     "anne": "DAYDAY DİDAY DAY",
     "kilo": "58,5",
     "jokey": "E.ATLAMAZ AP",
     "sahip": "BERKE KURTULUŞ",
     "antrenor": "İ.AKKILIÇ",
     "st": "4",
     "agf": "%20.12(1)",
     "h": "68",
     "son6": "K1K4K3Ç4K2K2",
     "kgs": "19",
     "s20": "19",
     "eniyi": ""
    },
    {
     "no": 2,
     "ad": "AMONİ DB SK",
     "yas": "3y d  d",
     "baba": "KULOĞLU",
     "anne": "PAN FLUTE",
     "kilo": "57,5",
     "jokey": "E.AKPINAR AP",
     "sahip": "CELAL CİNGÖZ",
     "antrenor": "E.ÇİLEK",
     "st": "1",
     "agf": "%13.6(5)",
     "h": "66",
     "son6": "K1Ç0K6K3K3K2",
     "kgs": "15",
     "s20": "15",
     "eniyi": ""
    },
    {
     "no": 3,
     "ad": "FINALLY ITS TIME KG DB SK",
     "yas": "3y d  d",
     "baba": "SUPER SAVER (USA)",
     "anne": "BLOOMY",
     "kilo": "59,5",
     "jokey": "M.M.BİLGİN",
     "sahip": "CUMA YILDIRIM",
     "antrenor": "M.AKKILIÇ",
     "st": "7",
     "agf": "%16.7(2)",
     "h": "64",
     "son6": "S2Ç4S7K1K2K6",
     "kgs": "19",
     "s20": "18",
     "eniyi": ""
    },
    {
     "no": 4,
     "ad": "ROSAS DEL ROSEDAL SK",
     "yas": "3y d  d",
     "baba": "KANEKO",
     "anne": "REAL GIRL",
     "kilo": "59",
     "jokey": "M.ÇİÇEK",
     "sahip": "SEMİH KATI",
     "antrenor": "H.SUNKAR",
     "st": "3",
     "agf": "%4.39(7)",
     "h": "63",
     "son6": "S3K4K2K8Ç0Ç8",
     "kgs": "12",
     "s20": "14",
     "eniyi": ""
    },
    {
     "no": 5,
     "ad": "FORTHCOMING QUEEN KG K DB",
     "yas": "3y d  d",
     "baba": "MENDIP (USA)",
     "anne": "EPONA",
     "kilo": "58",
     "jokey": "K.TOKAÇOĞLU",
     "sahip": "TAYRAL TUTUMLU",
     "antrenor": "Ş.AYDEMİR",
     "st": "6",
     "agf": "%4.24(8)",
     "h": "61",
     "son6": "K1K1K5K8K4K5",
     "kgs": "19",
     "s20": "16",
     "eniyi": ""
    },
    {
     "no": 6,
     "ad": "VAYNAKH SK",
     "yas": "3y d  d",
     "baba": "BLUEGRASS CAT (USA)",
     "anne": "RAPUNZEL",
     "kilo": "54,5",
     "jokey": "Y.GÖKÇE AP",
     "sahip": "ADİL MERT KAYA",
     "antrenor": "T.TAŞAR",
     "st": "5",
     "agf": "%15.62(4)",
     "h": "58",
     "son6": "S6S3Ç6Ç5Ç8K2",
     "kgs": "12",
     "s20": "14",
     "eniyi": ""
    },
    {
     "no": 7,
     "ad": "MISS CALIFORNIA KG K",
     "yas": "3y d  d",
     "baba": "SUPER SAVER (USA)",
     "anne": "AMERICAN BILLION",
     "kilo": "52",
     "jokey": "G.ÖZÇELİK",
     "sahip": "EMRAH ORHAN",
     "antrenor": "S.BEKTAŞ",
     "st": "8 - DS",
     "agf": "%9.47(6)",
     "h": "40",
     "son6": "S6S7K8K2K2K1",
     "kgs": "25",
     "s20": "20",
     "eniyi": "1:52.36"
    },
    {
     "no": 8,
     "ad": "MY HAZEL EYES DB SK",
     "yas": "3y d  d",
     "baba": "MER DE GLACE (JPN)",
     "anne": "ATEŞGEÇİRMEZ",
     "kilo": "52",
     "jokey": "S.TIRPAN",
     "sahip": "SEVDA ÖZGEN",
     "antrenor": "E.ÇİLEK",
     "st": "2",
     "agf": "%15.86(3)",
     "h": "33",
     "son6": "Ç0K0Ç0K2K3K2",
     "kgs": "7",
     "s20": "18",
     "eniyi": ""
    }
   ],
   "ikramiye": "630.000 TL",
   "odemeler": "7. ÇİFTE Bu koşudan başlar GANYAN İKİLİ SIRALI İKİLİ ÜÇLÜ BAHİS PLASE SABİT GANYAN SABİT İKİLİ SABİT SIRALI İKİLİ SABİT İLK 2 SABİT İLK 3 SABİT İLK 4"
  },
  {
   "no": 8,
   "saat": "21.30",
   "tur": "Handikap 14/DHÖW /H2",
   "grup": "4 ve Yukarı Araplar",
   "kilo": "kg",
   "mesafe": "2000m",
   "pist": "Kum",
   "horses": [
    {
     "no": 1,
     "ad": "HARPUT MUHAFIZI KG K DB",
     "yas": "4y d  a",
     "baba": "GELİBOLU",
     "anne": "SEYHATÇI",
     "kilo": "60",
     "jokey": "BERK.GÖKÇE AP",
     "sahip": "ERKUT ŞAHİN",
     "antrenor": "U.GÖKÇE",
     "st": "6",
     "agf": "%3.84(9)",
     "h": "47",
     "son6": "K7K1K5K4K5K8",
     "kgs": "93",
     "s20": "16",
     "eniyi": "2:26.97"
    },
    {
     "no": 2,
     "ad": "KIVIRCIKKIZ KG DB",
     "yas": "4y a k",
     "baba": "ÖZGÜNHAN",
     "anne": "HIZ TUTKUNU",
     "kilo": "61",
     "jokey": "G.ÖZÇELİK",
     "sahip": "FERAT ÖZKAN",
     "antrenor": "D.SAV",
     "st": "4",
     "agf": "%11.2(4)",
     "h": "45",
     "son6": "K7K3K2K4Ç2K3",
     "kgs": "7",
     "s20": "17",
     "eniyi": "2:25.19"
    },
    {
     "no": 3,
     "ad": "ZEMBEREK SKG SK",
     "yas": "5y a  a",
     "baba": "DİLİRAN",
     "anne": "TUNÇKANAT",
     "kilo": "60",
     "jokey": "Ç.TAŞCI AP",
     "sahip": "FATİH HAYIRLIOĞLU",
     "antrenor": "GÜV.GÖKÇE",
     "st": "9",
     "agf": "%7.82(6)",
     "h": "44",
     "son6": "S5K3K4Ç0K5K2",
     "kgs": "11",
     "s20": "16",
     "eniyi": "2:29.34"
    },
    {
     "no": 4,
     "ad": "TUTMAÇ KG DB",
     "yas": "4y a  a",
     "baba": "FİRİKYA",
     "anne": "YAKALA BENİ",
     "kilo": "58,5",
     "jokey": "M.M.BİLGİN",
     "sahip": "BERKCAN KESTEL",
     "antrenor": "MUR.AKKILIÇ",
     "st": "3",
     "agf": "%12.82(2)",
     "h": "40",
     "son6": "K4K3K2K3K4K8",
     "kgs": "21",
     "s20": "16",
     "eniyi": "2:27.32"
    },
    {
     "no": 5,
     "ad": "ZENG KG DB",
     "yas": "6y d  a",
     "baba": "TÜMÖZ BEY",
     "anne": "KAFKASLIDEVRANI",
     "kilo": "63",
     "jokey": "MAH.TURAN",
     "sahip": "ÖZKAN SAVRAN",
     "antrenor": "M.A.KAYA",
     "st": "11",
     "agf": "%10.42(3)",
     "h": "44",
     "son6": "K2K5K0Ç0K5K1",
     "kgs": "7",
     "s20": "20",
     "eniyi": ""
    },
    {
     "no": 6,
     "ad": "AFŞARBEY KG DB SK",
     "yas": "4y k  a",
     "baba": "TURBO",
     "anne": "İLK KIZ",
     "kilo": "56,5",
     "jokey": "A.ASLAN",
     "sahip": "HAKKI GÜLAL",
     "antrenor": "SEV.BEKTAŞ",
     "st": "5",
     "agf": "%4.5(8)",
     "h": "36",
     "son6": "K9Ç7Ç6Ç6K8K4",
     "kgs": "12",
     "s20": "8",
     "eniyi": "2:26.14"
    },
    {
     "no": 7,
     "ad": "KARANİMO DB",
     "yas": "5y d  a",
     "baba": "BABA MEVLÜT",
     "anne": "AKAY",
     "kilo": "58,5",
     "jokey": "O.ATMACA",
     "sahip": "KAAN GÜNEŞ",
     "antrenor": "K.GÜNEŞ",
     "st": "7",
     "agf": "%4.98(7)",
     "h": "35",
     "son6": "Ç9S6S6K0-K8K3",
     "kgs": "11",
     "s20": "14",
     "eniyi": "2:35.72"
    },
    {
     "no": 8,
     "ad": "COŞDUR DB SKG SK",
     "yas": "6y a  a",
     "baba": "COŞARTAY",
     "anne": "DURAK",
     "kilo": "56",
     "jokey": "Ö.F.ÖZEN AP",
     "sahip": "KEMAL ALTIN",
     "antrenor": "M.ALTIN",
     "st": "1",
     "agf": "%7.22(5)",
     "h": "34",
     "son6": "K6K2K6K2K9K5",
     "kgs": "11",
     "s20": "16",
     "eniyi": "2:25.79"
    },
    {
     "no": 9,
     "ad": "EMİRHAT KG DB SK",
     "yas": "4y a  a",
     "baba": "SERDÜMEN",
     "anne": "DESSAS",
     "kilo": "54,5",
     "jokey": "M.ÇELİK AP",
     "sahip": "KEMAL ALTIN",
     "antrenor": "M.ALTIN",
     "st": "8",
     "agf": "%1.84(5)",
     "h": "34",
     "son6": "K0K8K6K8K9K9",
     "kgs": "5",
     "s20": "14",
     "eniyi": "2:31.14"
    },
    {
     "no": 10,
     "ad": "BİRGEDAĞ KG K",
     "yas": "4y k  a",
     "baba": "GELİBOLU",
     "anne": "BOLKARIN GÜLÜ",
     "kilo": "54,5",
     "jokey": "S.TIRPAN",
     "sahip": "DEMİRHAN YILMAZ",
     "antrenor": "E.ÇİLEK",
     "st": "10",
     "agf": "%33.72(1)",
     "h": "32",
     "son6": "K6Ç0Ç6Ç0K2K3",
     "kgs": "12",
     "s20": "7",
     "eniyi": "2:27.32"
    },
    {
     "no": 11,
     "ad": "KARŞIYAKALI PİRENURİ KG SK",
     "yas": "4y k  g",
     "baba": "ALMAATA",
     "anne": "FİLDİŞİ",
     "kilo": "50",
     "jokey": "İ.GÜN AP",
     "sahip": "ÖZKAN SAVRAN",
     "antrenor": "M.A.KAYA",
     "st": "2",
     "agf": "%1.63(3)",
     "h": "12",
     "son6": "K7K8Ç0K9-K8",
     "kgs": "7",
     "s20": "15",
     "eniyi": ""
    }
   ],
   "ikramiye": "400.000 TL"
  }
 ]
}